Workbook

Sheet 1_Dataset
A1: Order ID | B1: Order Date | C1: Ship Date | D1: Customer Name | E1: Segment | F1: Region | G1: Category | H1: Sub-Category | I1: Product Name | J1: Sales | K1: Quantity | L1: Discount | M1: Profit
A2: ORD-0001 | B2: 2023-11-24 | C2: 2023-11-26 | D2: Leo Patel | E2: Home Office | F2: East | G2: Furniture | H2: Bookcases | I2: Glass Door Cabinet | J2: 749.78 | K2: 3 | L2: 0.3 | M2: -6.75
A3: ORD-0002 | B3: 2023-08-05 | C3: 2023-08-07 | D3: David Brown | E3: Home Office | F3: South | G3: Furniture | H3: Chairs | I3: Ergonomic Chair Pro | J3: 671.54 | K3: 9 | L3: 0.2 | M3: -26.45
A4: ORD-0003 | B4: 2023-08-18 | C4: 2023-08-24 | D4: Eva Green | E4: Consumer | F4: West | G4: Technology | H4: Phones | I4: iPhone 15 Pro | J4: 2281.25 | K4: 3 | L4: 0.3 | M4: 271.57
A5: ORD-0004 | B5: 2023-02-22 | C5: 2023-02-24 | D5: Alice Johnson | E5: Home Office | F5: South | G5: Technology | H5: Phones | I5: Pixel 8 | J5: 1089.76 | K5: 6 | L5: 0.2 | M5: 60.82
A6: ORD-0005 | B6: 2023-03-05 | C6: 2023-03-10 | D6: Leo Patel | E6: Consumer | F6: East | G6: Furniture | H6: Bookcases | I6: Glass Door Cabinet | J6: 2491.63 | K6: 10 | L6: 0 | M6: 450.84
A7: ORD-0006 | B7: 2023-04-27 | C7: 2023-05-01 | D7: Frank Lee | E7: Consumer | F7: Central | G7: Furniture | H7: Tables | I7: Conference Table | J7: 2602.12 | K7: 7 | L7: 0 | M7: 341.83
A8: ORD-0007 | B8: 2023-04-18 | C8: 2023-04-25 | D8: Carol White | E8: Corporate | F8: South | G8: Technology | H8: Phones | I8: iPhone 15 Pro | J8: 1835.21 | K8: 3 | L8: 0.2 | M8: 443.48
A9: ORD-0008 | B9: 2023-11-24 | C9: 2023-12-01 | D9: Frank Lee | E9: Corporate | F9: Central | G9: Office Supplies | H9: Binders | I9: 3-Ring Binder | J9: 2060.15 | K9: 1 | L9: 0 | M9: 574.21
A10: ORD-0009 | B10: 2023-04-19 | C10: 2023-04-25 | D10: Karen Singh | E10: Corporate | F10: West | G10: Office Supplies | H10: Storage | I10: Filing Cabinet | J10: 653.63 | K10: 8 | L10: 0.1 | M10: 198.62
A11: ORD-0010 | B11: 2023-03-13 | C11: 2023-03-16 | D11: Grace Kim | E11: Corporate | F11: West | G11: Office Supplies | H11: Labels | I11: Address Labels | J11: 1626.15 | K11: 10 | L11: 0.1 | M11: 502.69
A12: ORD-0011 | B12: 2023-09-18 | C12: 2023-09-23 | D12: Karen Singh | E12: Corporate | F12: East | G12: Furniture | H12: Chairs | I12: Mesh Task Chair | J12: 2586.09 | K12: 3 | L12: 0.3 | M12: 36.19
A13: ORD-0012 | B13: 2023-07-15 | C13: 2023-07-21 | D13: Karen Singh | E13: Home Office | F13: Central | G13: Technology | H13: Accessories | I13: Keyboard Pro | J13: 2913.81 | K13: 1 | L13: 0.3 | M13: 694.33
... A201: ORD-0200 | B201: 2023-03-02 | C201: 2023-03-09 | D201: Henry Park | E201: Home Office | F201: Central | G201: Technology | H201: Accessories | I201: Wireless Mouse | J201: 1851.58 | K201: 4 | L201: 0 | M201: 261.58

Sheet 2_DataCleaning
A1: DATA CLEANING & PREPARATION LOG
A2: Dataset: Superstore Sales 2023 | Source: Kaggle/UCI ML Repository
A4: Step | B4: Action | C4: Column(s) Affected | D4: Issue Found | E4: Resolution | F4: Status
A5: 1 | B5: Check for Duplicates | C5: Order ID | D5: No duplicates found (200 unique rows) | E5: Verified with COUNTIF formula | F5: ✔ Done
A6: 2 | B6: Handle Missing Values | C6: All Columns | D6: 0 blank cells detected | E6: No action needed | F6: ✔ Done
A7: 3 | B7: Format Order Date | C7: Order Date | D7: Dates stored as text strings | E7: Converted to YYYY-MM-DD format | F7: ✔ Done
A8: 4 | B8: Format Ship Date | C8: Ship Date | D8: Dates stored as text strings | E8: Converted to YYYY-MM-DD format | F8: ✔ Done
A9: 5 | B9: Validate Discount Range | C9: Discount | D9: Values must be between 0 and 1 | E9: Checked: all values in [0, 0.3] | F9: ✔ Done
A10: 6 | B10: Check Negative Profits | C10: Profit | D10: Some products sold at a loss | E10: Flagged in red; retained for analysis | F10: ✔ Done
A11: 7 | B11: Standardize Text Case | C11: Segment, Region | D11: Mixed casing observed | E11: Applied PROPER() normalization | F11: ✔ Done
A12: 8 | B12: Remove Leading/Trailing Spaces | C12: Customer Name | D12: Potential whitespace issues | E12: Applied TRIM() to name column | F12: ✔ Done
A13: 9 | B13: Validate Quantity (>0) | C13: Quantity | D13: Quantity must be positive integer | E13: All values validated ≥ 1 | F13: ✔ Done
A14: 10 | B14: Data Type Verification | C14: Sales, Profit | D14: Ensure numeric, not text | E14: Confirmed numeric format | F14: ✔ Done
A17: DATASET SUMMARY STATISTICS
A18: Metric | B18: Value
A19: Total Records | B19: =COUNTA('1_Dataset'!A2:A201) -> 200
A20: Total Sales | B20: =SUM('1_Dataset'!J2:J201) -> 301247.38
A21: Total Profit | B21: =SUM('1_Dataset'!M2:M201) -> 45095.84
A22: Average Discount | B22: =AVERAGE('1_Dataset'!L2:L201) -> 0.0965
A23: Unique Customers | B23: =SUMPRODUCT(1/COUNTIF('1_Dataset'!D2:D201,'1_Dataset'!D2:D201)) -> 12
A24: Profitable Orders | B24: =COUNTIF('1_Dataset'!M2:M201,">0") -> 174
A25: Loss-making Orders | B25: =COUNTIF('1_Dataset'!M2:M201,"<0") -> 26

Sheet 3_PivotTables
A1: PIVOT TABLE ANALYSIS
A3: Sales & Profit by Category | G3: Sales by Customer Segment
A4: Category | B4: Sum of Sales | C4: Sum of Profit | D4: Average of Discount | E4: Count of Order ID | G4: Row Labels | H4: Sum of Sales | I4: Sum of Profit
A5: Furniture | B5: 98809.24 | C5: 13726.07 | D5: 0.0984375 | E5: 64 | G5: Consumer | H5: 95569.27 | I5: 13594.12
A6: Office Supplies | B6: 95608.21 | C6: 14144.27 | D6: 0.1 | E6: 65 | G6: Corporate | H6: 103344.9 | I6: 17549.6
A7: Technology | B7: 106829.93 | C7: 17225.5 | D7: 0.091549296 | E7: 71 | G7: Home Office | H7: 102333.21 | I7: 13952.12
A8: Grand Total | B8: 301247.38 | C8: 45095.84 | D8: 0.0965 | E8: 200 | G8: Grand Total | H8: 301247.38 | I8: 45095.84
A11: Sales & Profit by Region
A12: Category | B12: Sum of Sales | C12: Sum of Profit | D12: Sum of Discount | E12: Count of Order ID
A13: Central | B13: 90039.33 | C13: 14210.86 | D13: 4.2 | E13: 56
A14: East | B14: 79782.68 | C14: 11968.7 | D14: 5.5 | E14: 49
A15: South | B15: 67162.95 | C15: 9256.37 | D15: 5.6 | E15: 51
A16: West | B16: 64262.42 | C16: 9659.91 | D16: 4 | E16: 44
A17: Grand Total | B17: 301247.38 | C17: 45095.84 | D17: 19.3 | E17: 200

Sheet 4_AdvancedFormulas
A1: ADVANCED FORMULA SHOWCASE
A3: VLOOKUP – Product Lookup
A4: Order ID to Lookup | B4: ORD-0042
A5: Customer Name | B5: =VLOOKUP(B4,'1_Dataset'!A$1:D$201,4,FALSE()) -> Grace Kim
A6: Segment | B6: =VLOOKUP(B4,'1_Dataset'!A$1:E$201,5,FALSE()) -> Home Office
A7: Sales ($) | B7: =VLOOKUP(B4,'1_Dataset'!A$1:J$201,10,FALSE()) -> 1230.1
A10: INDEX-MATCH – Dynamic Lookup
A11: Lookup Customer | B11: Alice Johnson
A12: First Order ID | B12: =INDEX('1_Dataset'!A$2:A$201,MATCH(B11,'1_Dataset'!D$2:D$201,0)) -> ORD-0004
A13: Category | B13: =INDEX('1_Dataset'!G$2:G$201,MATCH(B11,'1_Dataset'!D$2:D$201,0)) -> Technology
A14: Max Sales | B14: =SUMPRODUCT(MAX(('1_Dataset'!D$2:D$201=B11)*'1_Dataset'!J$2:J$201)) -> 2652.36
A17: IF / Nested IF – Profit Rating
A18: Order ID | B18: Sales | C18: Profit | D18: Rating | E18: Performance
A19: ='1_Dataset'!A2 -> ORD-0001 | B19: ='1_Dataset'!J2 -> 749.78 | C19: ='1_Dataset'!M2 -> -6.75 | D19: =IF(C19>500,"High",IF(C19>0,"Medium","Loss")) -> Loss | E19: =IF(B19>1000,"Top Seller",IF(B19>500,"Good","Below Avg")) -> Good
A20: ='1_Dataset'!A3 -> ORD-0002 | B20: ='1_Dataset'!J3 -> 671.54 | C20: ='1_Dataset'!M3 -> -26.45 | D20: =IF(C20>500,"High",IF(C20>0,"Medium","Loss")) -> Loss | E20: =IF(B20>1000,"Top Seller",IF(B20>500,"Good","Below Avg")) -> Good
A21: ='1_Dataset'!A4 -> ORD-0003 | B21: ='1_Dataset'!J4 -> 2281.25 | C21: ='1_Dataset'!M4 -> 271.57 | D21: =IF(C21>500,"High",IF(C21>0,"Medium","Loss")) -> Medium | E21: =IF(B21>1000,"Top Seller",IF(B21>500,"Good","Below Avg")) -> Top Seller
A22: ='1_Dataset'!A5 -> ORD-0004 | B22: ='1_Dataset'!J5 -> 1089.76 | C22: ='1_Dataset'!M5 -> 60.82 | D22: =IF(C22>500,"High",IF(C22>0,"Medium","Loss")) -> Medium | E22: =IF(B22>1000,"Top Seller",IF(B22>500,"Good","Below Avg")) -> Top Seller
A23: ='1_Dataset'!A6 -> ORD-0005 | B23: ='1_Dataset'!J6 -> 2491.63 | C23: ='1_Dataset'!M6 -> 450.84 | D23: =IF(C23>500,"High",IF(C23>0,"Medium","Loss")) -> Medium | E23: =IF(B23>1000,"Top Seller",IF(B23>500,"Good","Below Avg")) -> Top Seller
A24: ='1_Dataset'!A7 -> ORD-0006 | B24: ='1_Dataset'!J7 -> 2602.12 | C24: ='1_Dataset'!M7 -> 341.83 | D24: =IF(C24>500,"High",IF(C24>0,"Medium","Loss")) -> Medium | E24: =IF(B24>1000,"Top Seller",IF(B24>500,"Good","Below Avg")) -> Top Seller
A25: ='1_Dataset'!A8 -> ORD-0007 | B25: ='1_Dataset'!J8 -> 1835.21 | C25: ='1_Dataset'!M8 -> 443.48 | D25: =IF(C25>500,"High",IF(C25>0,"Medium","Loss")) -> Medium | E25: =IF(B25>1000,"Top Seller",IF(B25>500,"Good","Below Avg")) -> Top Seller
A26: ='1_Dataset'!A9 -> ORD-0008 | B26: ='1_Dataset'!J9 -> 2060.15 | C26: ='1_Dataset'!M9 -> 574.21 | D26: =IF(C26>500,"High",IF(C26>0,"Medium","Loss")) -> High | E26: =IF(B26>1000,"Top Seller",IF(B26>500,"Good","Below Avg")) -> Top Seller
A27: Category | B27: Count | C27: Total Sales | D27: Total Profit | E27: Avg Sales
A28: Furniture | B28: =COUNTIF('1_Dataset'!G$2:G$201,A28) -> 64 | C28: =SUMIF('1_Dataset'!G$2:G$201,A28,'1_Dataset'!J$2:J$201) -> 98809.24 | D28: =SUMIF('1_Dataset'!G$2:G$201,A28,'1_Dataset'!M$2:M$201) -> 13726.07 | E28: =AVERAGEIF('1_Dataset'!G$2:G$201,A28,'1_Dataset'!J$2:J$201) -> 1543.8944
A29: Office Supplies | B29: =COUNTIF('1_Dataset'!G$2:G$201,A29) -> 65 | C29: =SUMIF('1_Dataset'!G$2:G$201,A29,'1_Dataset'!J$2:J$201) -> 95608.21 | D29: =SUMIF('1_Dataset'!G$2:G$201,A29,'1_Dataset'!M$2:M$201) -> 14144.27 | E29: =AVERAGEIF('1_Dataset'!G$2:G$201,A29,'1_Dataset'!J$2:J$201) -> 1470.8955
A30: Technology | B30: =COUNTIF('1_Dataset'!G$2:G$201,A30) -> 71 | C30: =SUMIF('1_Dataset'!G$2:G$201,A30,'1_Dataset'!J$2:J$201) -> 106829.93 | D30: =SUMIF('1_Dataset'!G$2:G$201,A30,'1_Dataset'!M$2:M$201) -> 17225.5 | E30: =AVERAGEIF('1_Dataset'!G$2:G$201,A30,'1_Dataset'!J$2:J$201) -> 1504.6469
A34: TEXT Functions
A35: Sample Date | B35: TEXT Formula | C35: Formatted Date | D35: Month Name | E35: Year
A36: 2023-03-15 | B36: =TEXT(A36,"DD/MM/YYYY") -> 15/03/2023 | C36: =TEXT(A36,"MMMM DD, YYYY") -> March 15, 2023 | D36: =TEXT(A36,"MMMM") -> March | E36: =TEXT(A36,"YYYY") -> 2023
A37: 2023-07-04 | B37: =TEXT(A37,"DD/MM/YYYY") -> 04/07/2023 | C37: =TEXT(A37,"MMMM DD, YYYY") -> July 04, 2023 | D37: =TEXT(A37,"MMMM") -> July | E37: =TEXT(A37,"YYYY") -> 2023
A38: 2023-11-28 | B38: =TEXT(A38,"DD/MM/YYYY") -> 28/11/2023 | C38: =TEXT(A38,"MMMM DD, YYYY") -> November 28, 2023 | D38: =TEXT(A38,"MMMM") -> November | E38: =TEXT(A38,"YYYY") -> 2023
A39: 2023-01-01 | B39: =TEXT(A39,"DD/MM/YYYY") -> 01/01/2023 | C39: =TEXT(A39,"MMMM DD, YYYY") -> January 01, 2023 | D39: =TEXT(A39,"MMMM") -> January | E39: =TEXT(A39,"YYYY") -> 2023
A40: 2023-12-31 | B40: =TEXT(A40,"DD/MM/YYYY") -> 31/12/2023 | C40: =TEXT(A40,"MMMM DD, YYYY") -> December 31, 2023 | D40: =TEXT(A40,"MMMM") -> December | E40: =TEXT(A40,"YYYY") -> 2023

Sheet 5_DataVisualization
A1: DATA VISUALIZATION – CHARTS & CONDITIONAL FORMATTING
A3: Category | B3: Sales | C3: Profit | E3: Region | F3: Sales
A4: Furniture | B4: =SUMIF('1_Dataset'!G$2:G$201,A4,'1_Dataset'!J$2:J$201) -> 98809.24 | C4: =SUMIF('1_Dataset'!G$2:G$201,A4,'1_Dataset'!M$2:M$201) -> 13726.07 | E4: East | F4: =SUMIF('1_Dataset'!F$2:F$201,E4,'1_Dataset'!J$2:J$201) -> 79782.68
A5: Office Supplies | B5: =SUMIF('1_Dataset'!G$2:G$201,A5,'1_Dataset'!J$2:J$201) -> 95608.21 | C5: =SUMIF('1_Dataset'!G$2:G$201,A5,'1_Dataset'!M$2:M$201) -> 14144.27 | E5: West | F5: =SUMIF('1_Dataset'!F$2:F$201,E5,'1_Dataset'!J$2:J$201) -> 64262.42
A6: Technology | B6: =SUMIF('1_Dataset'!G$2:G$201,A6,'1_Dataset'!J$2:J$201) -> 106829.93 | C6: =SUMIF('1_Dataset'!G$2:G$201,A6,'1_Dataset'!M$2:M$201) -> 17225.5 | E6: Central | F6: =SUMIF('1_Dataset'!F$2:F$201,E6,'1_Dataset'!J$2:J$201) -> 90039.33
E7: South | F7: =SUMIF('1_Dataset'!F$2:F$201,E7,'1_Dataset'!J$2:J$201) -> 67162.95
A28: CONDITIONAL FORMATTING EXAMPLES
A29: Order ID | B29: Sales | C29: Profit | D29: Discount | E29: Category | F29: CF Applied
A30: ='1_Dataset'!A2 -> ORD-0001 | B30: ='1_Dataset'!J2 -> 749.78 | C30: ='1_Dataset'!M2 -> -6.75 | D30: ='1_Dataset'!L2 -> 0.3 | E30: ='1_Dataset'!G2 -> Furniture | F30: Auto
A31: ='1_Dataset'!A3 -> ORD-0002 | B31: ='1_Dataset'!J3 -> 671.54 | C31: ='1_Dataset'!M3 -> -26.45 | D31: ='1_Dataset'!L3 -> 0.2 | E31: ='1_Dataset'!G3 -> Furniture | F31: Auto
A32: ='1_Dataset'!A4 -> ORD-0003 | B32: ='1_Dataset'!J4 -> 2281.25 | C32: ='1_Dataset'!M4 -> 271.57 | D32: ='1_Dataset'!L4 -> 0.3 | E32: ='1_Dataset'!G4 -> Technology | F32: Auto
A33: ='1_Dataset'!A5 -> ORD-0004 | B33: ='1_Dataset'!J5 -> 1089.76 | C33: ='1_Dataset'!M5 -> 60.82 | D33: ='1_Dataset'!L5 -> 0.2 | E33: ='1_Dataset'!G5 -> Technology | F33: Auto
A34: ='1_Dataset'!A6 -> ORD-0005 | B34: ='1_Dataset'!J6 -> 2491.63 | C34: ='1_Dataset'!M6 -> 450.84 | D34: ='1_Dataset'!L6 -> 0 | E34: ='1_Dataset'!G6 -> Furniture | F34: Auto
A35: ='1_Dataset'!A7 -> ORD-0006 | B35: ='1_Dataset'!J7 -> 2602.12 | C35: ='1_Dataset'!M7 -> 341.83 | D35: ='1_Dataset'!L7 -> 0 | E35: ='1_Dataset'!G7 -> Furniture | F35: Auto
A36: ='1_Dataset'!A8 -> ORD-0007 | B36: ='1_Dataset'!J8 -> 1835.21 | C36: ='1_Dataset'!M8 -> 443.48 | D36: ='1_Dataset'!L8 -> 0.2 | E36: ='1_Dataset'!G8 -> Technology | F36: Auto
A37: ='1_Dataset'!A9 -> ORD-0008 | B37: ='1_Dataset'!J9 -> 2060.15 | C37: ='1_Dataset'!M9 -> 574.21 | D37: ='1_Dataset'!L9 -> 0 | E37: ='1_Dataset'!G9 -> Office Supplies | F37: Auto
A38: ='1_Dataset'!A10 -> ORD-0009 | B38: ='1_Dataset'!J10 -> 653.63 | C38: ='1_Dataset'!M10 -> 198.62 | D38: ='1_Dataset'!L10 -> 0.1 | E38: ='1_Dataset'!G10 -> Office Supplies | F38: Auto
A39: ='1_Dataset'!A11 -> ORD-0010 | B39: ='1_Dataset'!J11 -> 1626.15 | C39: ='1_Dataset'!M11 -> 502.69 | D39: ='1_Dataset'!L11 -> 0.1 | E39: ='1_Dataset'!G11 -> Office Supplies | F39: Auto
A40: ='1_Dataset'!A12 -> ORD-0011 | B40: ='1_Dataset'!J12 -> 2586.09 | C40: ='1_Dataset'!M12 -> 36.19 | D40: ='1_Dataset'!L12 -> 0.3 | E40: ='1_Dataset'!G12 -> Furniture | F40: Auto
A41: ='1_Dataset'!A13 -> ORD-0012 | B41: ='1_Dataset'!J13 -> 2913.81 | C41: ='1_Dataset'!M13 -> 694.33 | D41: ='1_Dataset'!L13 -> 0.3 | E41: ='1_Dataset'!G13 -> Technology | F41: Auto
... A44: ='1_Dataset'!A16 -> ORD-0015 | B44: ='1_Dataset'!J16 -> 733.57 | C44: ='1_Dataset'!M16 -> 241.18 | D44: ='1_Dataset'!L16 -> 0.2 | E44: ='1_Dataset'!G16 -> Technology | F44: Auto

Sheet 6_Dashboard
A1: 📊 SUPERSTORE SALES INTERACTIVE DASHBOARD 📊
A3: 💰 | D3: 📈 | G3: 📦 | J3: 🏷️ | M3: 💹
A4: TOTAL SALES | D4: TOTAL PROFIT | G4: TOTAL ORDERS | J4: AVG DISCOUNT | M4: PROFIT MARGIN
A5: =SUM('1_Dataset'!J2:J201) -> 301247.38 | D5: =SUM('1_Dataset'!M2:M201) -> 45095.84 | G5: =COUNTA('1_Dataset'!A2:A201) -> 200 | J5: =AVERAGE('1_Dataset'!L2:L201) -> 0.0965 | M5: =SUM('1_Dataset'!M2:M201)/SUM('1_Dataset'!J2:J201) -> 0.14969704
A7: Sales by Category | E7: Sales by Region | I7: Sales by Segment | M7: Top 5 Sub-Categories by Sales
A8: Category | B8: Sales | C8: Profit | E8: Region | F8: Sales | G8: Profit | I8: Segment | J8: Sales | K8: Profit | M8: Sub-Cat | N8: Sales | O8: Profit | P8: #Orders
A9: Furniture | B9: =SUMIF('1_Dataset'!G$2:G$201,A9,'1_Dataset'!J$2:J$201) -> 98809.24 | C9: =SUMIF('1_Dataset'!G$2:G$201,A9,'1_Dataset'!M$2:M$201) -> 13726.07 | E9: East | F9: =SUMIF('1_Dataset'!F$2:F$201,E9,'1_Dataset'!J$2:J$201) -> 79782.68 | G9: =SUMIF('1_Dataset'!F$2:F$201,E9,'1_Dataset'!M$2:M$201) -> 11968.7 | I9: Consumer | J9: =SUMIF('1_Dataset'!E$2:E$201,I9,'1_Dataset'!J$2:J$201) -> 95569.27 | K9: =SUMIF('1_Dataset'!E$2:E$201,I9,'1_Dataset'!M$2:M$201) -> 13594.12 | M9: Phones | N9: =SUMIF('1_Dataset'!H$2:H$201,M9,'1_Dataset'!J$2:J$201) -> 26191.29 | O9: =SUMIF('1_Dataset'!H$2:H$201,M9,'1_Dataset'!M$2:M$201) -> 5404.12 | P9: =COUNTIF('1_Dataset'!H$2:H$201,M9) -> 20
A10: Office Supplies | B10: =SUMIF('1_Dataset'!G$2:G$201,A10,'1_Dataset'!J$2:J$201) -> 95608.21 | C10: =SUMIF('1_Dataset'!G$2:G$201,A10,'1_Dataset'!M$2:M$201) -> 14144.27 | E10: West | F10: =SUMIF('1_Dataset'!F$2:F$201,E10,'1_Dataset'!J$2:J$201) -> 64262.42 | G10: =SUMIF('1_Dataset'!F$2:F$201,E10,'1_Dataset'!M$2:M$201) -> 9659.91 | I10: Corporate | J10: =SUMIF('1_Dataset'!E$2:E$201,I10,'1_Dataset'!J$2:J$201) -> 103344.9 | K10: =SUMIF('1_Dataset'!E$2:E$201,I10,'1_Dataset'!M$2:M$201) -> 17549.6 | M10: Chairs | N10: =SUMIF('1_Dataset'!H$2:H$201,M10,'1_Dataset'!J$2:J$201) -> 25465.15 | O10: =SUMIF('1_Dataset'!H$2:H$201,M10,'1_Dataset'!M$2:M$201) -> 2758.96 | P10: =COUNTIF('1_Dataset'!H$2:H$201,M10) -> 17
A11: Technology | B11: =SUMIF('1_Dataset'!G$2:G$201,A11,'1_Dataset'!J$2:J$201) -> 106829.93 | C11: =SUMIF('1_Dataset'!G$2:G$201,A11,'1_Dataset'!M$2:M$201) -> 17225.5 | E11: Central | F11: =SUMIF('1_Dataset'!F$2:F$201,E11,'1_Dataset'!J$2:J$201) -> 90039.33 | G11: =SUMIF('1_Dataset'!F$2:F$201,E11,'1_Dataset'!M$2:M$201) -> 14210.86 | I11: Home Office | J11: =SUMIF('1_Dataset'!E$2:E$201,I11,'1_Dataset'!J$2:J$201) -> 102333.21 | K11: =SUMIF('1_Dataset'!E$2:E$201,I11,'1_Dataset'!M$2:M$201) -> 13952.12 | M11: Tables | N11: =SUMIF('1_Dataset'!H$2:H$201,M11,'1_Dataset'!J$2:J$201) -> 27674.33 | O11: =SUMIF('1_Dataset'!H$2:H$201,M11,'1_Dataset'!M$2:M$201) -> 4098.11 | P11: =COUNTIF('1_Dataset'!H$2:H$201,M11) -> 15
E12: South | F12: =SUMIF('1_Dataset'!F$2:F$201,E12,'1_Dataset'!J$2:J$201) -> 67162.95 | G12: =SUMIF('1_Dataset'!F$2:F$201,E12,'1_Dataset'!M$2:M$201) -> 9256.37 | M12: Accessories | N12: =SUMIF('1_Dataset'!H$2:H$201,M12,'1_Dataset'!J$2:J$201) -> 25011.35 | O12: =SUMIF('1_Dataset'!H$2:H$201,M12,'1_Dataset'!M$2:M$201) -> 4617.3 | P12: =COUNTIF('1_Dataset'!H$2:H$201,M12) -> 14
M13: Binders | N13: =SUMIF('1_Dataset'!H$2:H$201,M13,'1_Dataset'!J$2:J$201) -> 21552.23 | O13: =SUMIF('1_Dataset'!H$2:H$201,M13,'1_Dataset'!M$2:M$201) -> 3000.88 | P13: =COUNTIF('1_Dataset'!H$2:H$201,M13) -> 17
P35: -

Sheet 7_Documentation
A1: WORKBOOK DOCUMENTATION & INSTRUCTIONS
A3: SHEET INDEX
A4: Sheet Name | B4: Description | C4: Skills Demonstrated | D4: Weightage
A5: 1_Dataset | B5: 200 rows of Superstore Sales data (orders, customers, products, financials) | C5: Data Import, Cleaning | D5: 5%
A6: 2_DataCleaning | B6: Documented data cleaning steps, summary statistics, and quality checks | C6: Remove duplicates, Handle missing values, Format data | D6: 10%
A7: 3_PivotTables | B7: Manual pivot-style summaries: Sales by Category, Region, and Segment | C7: Data Analysis, Summarization | D7: 15%
A8: 4_AdvancedFormulas | B8: VLOOKUP, INDEX-MATCH, IF/nested IF, COUNTIF/SUMIF, TEXT functions | C8: VLOOKUP, INDEX-MATCH, IF conditions, nested functions | D8: 15%
A9: 5_DataVisualization | B9: Bar chart, Pie chart, Conditional Formatting (Data Bars, Color Scale) | C9: Charts, Conditional Formatting | D9: 20%
A10: 6_Dashboard | B10: Interactive KPI dashboard with charts and summary tables | C10: Slicers, Dynamic ranges, Dashboard design | D10: 25%
A11: 7_Documentation | B11: This sheet – instructions, naming conventions, and usage guide | C11: Sheet organization, Naming conventions | D11: 10%
A13: NAMING CONVENTIONS
A14: Element | B14: Convention | C14: Reason | D14: Notes
A15: File Name | B15: YourName_ExcelDashboard.xlsx | C15: Standard submission format
A16: Sheets | B16: N#_SheetName (e.g. 1_Dataset) | C16: Numbered for clear navigation
A17: Headers | B17: Bold, colored background | C17: Consistent across all sheets
A18: Data Rows | B18: Alternating White/Light Gray | C18: Improves readability
A19: Formulas | B19: Excel formulas, not hardcoded | C19: Dynamic and recalculable
A20: Currency | B20: $#,##0.00 format | C20: Consistent financial display
A21: Percentages | B21: 0.0% format | C21: One decimal place standard
A23: HOW TO USE THIS WORKBOOK
A24: 1. START HERE: Navigate using the sheet tabs at the bottom (1_Dataset → 7_Documentation).
A25: 2. DATASET: Sheet 1 contains 200 rows of sample Superstore Sales data with auto-filter enabled.
A26: 3. CLEANING: Sheet 2 documents all cleaning steps applied and provides summary statistics.
A27: 4. PIVOT TABLES: Sheet 3 shows aggregated analysis by Category, Region, and Segment using SUMIF formulas.
A28: 5. FORMULAS: Sheet 4 demonstrates VLOOKUP, INDEX-MATCH, IF conditions, COUNTIF/SUMIF, and TEXT functions.
A29: 6. CHARTS: Sheet 5 includes Bar and Pie charts plus Conditional Formatting (Data Bars & Color Scale).
A30: 7. DASHBOARD: Sheet 6 is the main dashboard with KPI cards, summary tables, and charts.
A31: 8. SLICERS: To add Slicers on Dashboard, go to Insert > Slicer and connect to the dataset.
A32: 9. SAVE: Use Ctrl+S every 15 minutes as per exam instructions.
A33: 10. SUBMIT: Rename as 'YourName_ExcelDashboard.xlsx' before submitting.
A35: Created: Superstore Sales Dashboard | Total Time Estimate: 210 min | Total Weightage: 100%
