Workbook

Sheet Raw Data
A1: Transaction_ID | B1: Date | C1: Customer_ID | D1: Customer_Name | E1: Product_ID | F1: Product_Name | G1: Category | H1: Quantity | I1: Unit_Price | J1: Payment_Method | K1: Region | L1: Customer_Segment | M1: Customer_Since | N1: Total_Amount
A2: TRX0155 | B2: 2024-04-11 | C2: CUST023 | D2: Paul Baker | E2: P009 | F2: Monitor | G2: Electronics | H2: 3 | I2: 249.99 | J2: Cash | K2: Central | L2: Basic | M2: 2021-08-17 | N2: 749.97
A3: TRX0023 | B3: 2024-04-14 | C3: CUST013 | D3: Joseph Jackson | E3: P009 | F3: Monitor | G3: Electronics | H3: 3 | I3: 249.99 | J3: Credit Card | K3: Central | L3: Premium | M3: 2022-01-14 | N3: 749.97
A4: TRX0139 | B4: 2024-04-17 | C4: CUST021 | D4: Kevin Scott | E4: P005 | F4: Blender | G4: Appliances | H4: 3 | I4: 59.99 | J4: PayPal | K4: South | L4: Standard | M4: 2023-12-02 | N4: 179.97
A5: TRX0043 | B5: 2024-04-18 | C5: CUST046 | D5: Kathleen Bennett | E5: P005 | F5: Blender | G5: Appliances | H5: 3 | I5: 59.99 | J5: Cash | K5: North | L5: Premium | M5: 2023-07-07 | N5: 179.97
A6: TRX0212 | B6: 2024-04-18 | C6: CUST003 | D6: Michael Brown | E6: P008 | F6: Bookshelf | G6: Furniture | H6: 5 | I6: 149.99 | J6: Credit Card | K6: North | L6: Premium | M6: 2024-01-04 | N6: 749.95
A7: TRX0092 | B7: 2024-04-21 | C7: CUST024 | D7: Dorothy Nelson | E7: P005 | F7: Blender | G7: Appliances | H7: 2 | I7: 59.99 | J7: Cash | K7: West | L7: Standard | M7: 2022-07-04 | N7: 119.98
A8: TRX0193 | B8: 2024-04-21 | C8: CUST024 | D8: Dorothy Nelson | E8: P003 | F8: Headphones | G8: Electronics | H8: 5 | I8: 149.99 | J8: Credit Card | K8: Central | L8: Standard | M8: 2021-08-10 | N8: 749.95
A9: TRX0240 | B9: 2024-04-21 | C9: CUST017 | D9: Charles Allen | E9: P005 | F9: Blender | G9: Appliances | H9: 3 | I9: 59.99 | J9: Debit Card | K9: South | L9: Basic | M9: 2023-03-22 | N9: 179.97
A10: TRX0135 | B10: 2024-04-23 | C10: CUST009 | D10: Robert Thomas | E10: P001 | F10: Laptop | G10: Electronics | H10: 3 | I10: 899.99 | J10: PayPal | K10: East | L10: Standard | M10: 2024-01-08 | N10: 2699.97
A11: TRX0185 | B11: 2024-04-26 | C11: CUST026 | D11: Karen Hill | E11: P005 | F11: Blender | G11: Appliances | H11: 3 | I11: 59.99 | J11: Cash | K11: West | L11: Premium | M11: 2023-10-08 | N11: 179.97
A12: TRX0138 | B12: 2024-04-26 | C12: CUST022 | D12: Susan Green | E12: P008 | F12: Bookshelf | G12: Furniture | H12: 1 | I12: 149.99 | J12: Credit Card | K12: West | L12: Standard | M12: 2023-06-26 | N12: 149.99
A13: TRX0209 | B13: 2024-04-26 | C13: CUST046 | D13: Kathleen Bennett | E13: P008 | F13: Bookshelf | G13: Furniture | H13: 5 | I13: 149.99 | J13: Debit Card | K13: North | L13: Basic | M13: 2022-09-26 | N13: 749.95
... A251: TRX0064 | B251: 2025-04-11 | C251: CUST031 | D251: Steven Turner | E251: P010 | F251: Keyboard | G251: Electronics | H251: 3 | I251: 89.99 | J251: Debit Card | K251: North | L251: Premium | M251: 2022-11-13 | N251: 269.97

Sheet Analysis
A1: 📅 DATE & TIME ANALYSIS
A2: Metric | D2: Value
A3: TODAY() | D3: =TODAY() -> 46110
A4: NOW() | D4: =NOW() -> 46110.453
A5: Report Generated On | D5: =TEXT(NOW(),"DD-MMM-YYYY HH:MM") -> 29-Mar-2026 10:51
A6: Data Start Date | D6: =MIN('Raw Data'!B:B) -> 0
A7: Data End Date | D7: =MAX('Raw Data'!B:B) -> 0
A8: Days Spanned (DATEDIF) | D8: =DATEDIF(MIN('Raw Data'!B:B),MAX('Raw Data'!B:B),"D") -> 0
A9: End of Data Month (EOMONTH) | D9: =EOMONTH(MAX('Raw Data'!B:B),0) -> 31
A10: Months Covered (DATEDIF) | D10: =DATEDIF(MIN('Raw Data'!B:B),MAX('Raw Data'!B:B),"M") -> 0
A13: 📊 KEY PERFORMANCE INDICATORS
A14: KPI | D14: Value
A15: Total Revenue | D15: =SUM('Raw Data'!N2:N10000) -> 229192.47
A16: Total Transactions | D16: =COUNTA('Raw Data'!A2:A10000) -> 250
A17: Average Order Value | D17: =IFERROR(AVERAGE('Raw Data'!N2:N10000),0) -> 916.76988
A18: Total Units Sold | D18: =SUM('Raw Data'!H2:H10000) -> 753
A19: Unique Customers | D19: =SUMPRODUCT(1/COUNTIF('Raw Data'!C2:C251,'Raw Data'!C2:C251)) -> 50
A20: Unique Products | D20: =SUMPRODUCT(1/COUNTIF('Raw Data'!E2:E251,'Raw Data'!E2:E251)) -> 10
A21: Max Single Order | D21: =MAX('Raw Data'!N2:N10000) -> 4499.95
A22: Min Single Order | D22: =MIN('Raw Data'!N2:N10000) -> 59.99
A25: 🏷️ REVENUE BY CATEGORY
A26: Category | B26: Revenue | C26: Transactions | D26: Units Sold | E26: Avg Order | F26: % of Revenue
A27: Electronics | B27: =SUMIF('Raw Data'!G:G,A27,'Raw Data'!N:N) -> 171756.05 | C27: =COUNTIF('Raw Data'!G:G,A27) -> 131 | D27: =SUMIF('Raw Data'!G:G,A27,'Raw Data'!H:H) -> 395 | E27: =IFERROR(B27/C27,0) -> 1311.1149 | F27: =IFERROR(B27/SUM(B27:B29),0) -> 0.74939657
A28: Furniture | B28: =SUMIF('Raw Data'!G:G,A28,'Raw Data'!N:N) -> 49097.68 | C28: =COUNTIF('Raw Data'!G:G,A28) -> 76 | D28: =SUMIF('Raw Data'!G:G,A28,'Raw Data'!H:H) -> 232 | E28: =IFERROR(B28/C28,0) -> 646.02211 | F28: =IFERROR(B28/SUM(B27:B29),0) -> 0.2142203
A29: Appliances | B29: =SUMIF('Raw Data'!G:G,A29,'Raw Data'!N:N) -> 8338.74 | C29: =COUNTIF('Raw Data'!G:G,A29) -> 43 | D29: =SUMIF('Raw Data'!G:G,A29,'Raw Data'!H:H) -> 126 | E29: =IFERROR(B29/C29,0) -> 193.92419 | F29: =IFERROR(B29/SUM(B27:B29),0) -> 0.036383132
A31: 🌍 REVENUE BY REGION
A32: Region | B32: Revenue | C32: Transactions | D32: Units Sold | E32: Avg Order | F32: % of Revenue
A33: Central | B33: =SUMIF('Raw Data'!K:K,A33,'Raw Data'!N:N) -> 41288.34 | C33: =COUNTIF('Raw Data'!K:K,A33) -> 54 | D33: =SUMIF('Raw Data'!K:K,A33,'Raw Data'!H:H) -> 166 | E33: =IFERROR(B33/C33,0) -> 764.59889 | F33: =IFERROR(B33/SUM(B33:B37),0) -> 0.18014702
A34: East | B34: =SUMIF('Raw Data'!K:K,A34,'Raw Data'!N:N) -> 59288.39 | C34: =COUNTIF('Raw Data'!K:K,A34) -> 48 | D34: =SUMIF('Raw Data'!K:K,A34,'Raw Data'!H:H) -> 161 | E34: =IFERROR(B34/C34,0) -> 1235.1748 | F34: =IFERROR(B34/SUM(B33:B37),0) -> 0.25868385
A35: North | B35: =SUMIF('Raw Data'!K:K,A35,'Raw Data'!N:N) -> 50808.31 | C35: =COUNTIF('Raw Data'!K:K,A35) -> 59 | D35: =SUMIF('Raw Data'!K:K,A35,'Raw Data'!H:H) -> 169 | E35: =IFERROR(B35/C35,0) -> 861.1578 | F35: =IFERROR(B35/SUM(B33:B37),0) -> 0.22168403
A36: South | B36: =SUMIF('Raw Data'!K:K,A36,'Raw Data'!N:N) -> 36398.75 | C36: =COUNTIF('Raw Data'!K:K,A36) -> 42 | D36: =SUMIF('Raw Data'!K:K,A36,'Raw Data'!H:H) -> 125 | E36: =IFERROR(B36/C36,0) -> 866.6369 | F36: =IFERROR(B36/SUM(B33:B37),0) -> 0.15881303
A37: West | B37: =SUMIF('Raw Data'!K:K,A37,'Raw Data'!N:N) -> 41408.68 | C37: =COUNTIF('Raw Data'!K:K,A37) -> 47 | D37: =SUMIF('Raw Data'!K:K,A37,'Raw Data'!H:H) -> 132 | E37: =IFERROR(B37/C37,0) -> 881.03574 | F37: =IFERROR(B37/SUM(B33:B37),0) -> 0.18067208
A40: 👥 CUSTOMER SEGMENT ANALYSIS
A41: Segment | B41: Revenue | C41: Transactions | D41: Avg Order | E41: % Revenue | F41: Rank
A42: Basic | B42: =SUMIF('Raw Data'!L:L,A42,'Raw Data'!N:N) -> 62177.81 | C42: =COUNTIF('Raw Data'!L:L,A42) -> 74 | D42: =IFERROR(B42/C42,0) -> 840.24068 | E42: =IFERROR(B42/SUM(B42:B44),0) -> 0.27129081 | F42: =RANK(B42,B42:B44,0) -> 3
A43: Premium | B43: =SUMIF('Raw Data'!L:L,A43,'Raw Data'!N:N) -> 84657.12 | C43: =COUNTIF('Raw Data'!L:L,A43) -> 95 | D43: =IFERROR(B43/C43,0) -> 891.12758 | E43: =IFERROR(B43/SUM(B42:B44),0) -> 0.3693713 | F43: =RANK(B43,B42:B44,0) -> 1
A44: Standard | B44: =SUMIF('Raw Data'!L:L,A44,'Raw Data'!N:N) -> 82357.54 | C44: =COUNTIF('Raw Data'!L:L,A44) -> 81 | D44: =IFERROR(B44/C44,0) -> 1016.7598 | E44: =IFERROR(B44/SUM(B42:B44),0) -> 0.3593379 | F44: =RANK(B44,B42:B44,0) -> 2
A47: 🏆 TOP 10 HIGH-VALUE CUSTOMERS (GroupBy Concept)
A48: Rank | B48: Customer Name | C48: Customer ID | D48: Total Revenue | E48: Transactions | F48: Avg Order | G48: Segment | H48: Region
A49: 1 | B49: Mark Carter | C49: CUST025 | D49: =SUMIF('Raw Data'!C:C,C49,'Raw Data'!N:N) -> 15659.65 | E49: =COUNTIF('Raw Data'!C:C,C49) -> 12 | F49: =IFERROR(D49/E49,0) -> 1304.9708 | G49: Standard | H49: West
A50: 2 | B50: Edward Mitchell | C50: CUST029 | D50: =SUMIF('Raw Data'!C:C,C50,'Raw Data'!N:N) -> 11919.77 | E50: =COUNTIF('Raw Data'!C:C,C50) -> 6 | F50: =IFERROR(D50/E50,0) -> 1986.6283 | G50: Standard | H50: Central
A51: 3 | B51: Barbara Young | C51: CUST018 | D51: =SUMIF('Raw Data'!C:C,C51,'Raw Data'!N:N) -> 10649.8 | E51: =COUNTIF('Raw Data'!C:C,C51) -> 5 | F51: =IFERROR(D51/E51,0) -> 2129.96 | G51: Standard | H51: East
A52: 4 | B52: Patricia Moore | C52: CUST012 | D52: =SUMIF('Raw Data'!C:C,C52,'Raw Data'!N:N) -> 9799.73 | E52: =COUNTIF('Raw Data'!C:C,C52) -> 8 | F52: =IFERROR(D52/E52,0) -> 1224.9662 | G52: Standard | H52: West
A53: 5 | B53: Paul Baker | C53: CUST023 | D53: =SUMIF('Raw Data'!C:C,C53,'Raw Data'!N:N) -> 8309.74 | E53: =COUNTIF('Raw Data'!C:C,C53) -> 8 | F53: =IFERROR(D53/E53,0) -> 1038.7175 | G53: Premium | H53: West
A54: 6 | B54: Dorothy Nelson | C54: CUST024 | D54: =SUMIF('Raw Data'!C:C,C54,'Raw Data'!N:N) -> 8269.79 | E54: =COUNTIF('Raw Data'!C:C,C54) -> 6 | F54: =IFERROR(D54/E54,0) -> 1378.2983 | G54: Basic | H54: North
A55: 7 | B55: Karen Hill | C55: CUST026 | D55: =SUMIF('Raw Data'!C:C,C55,'Raw Data'!N:N) -> 8009.77 | E55: =COUNTIF('Raw Data'!C:C,C55) -> 8 | F55: =IFERROR(D55/E55,0) -> 1001.2212 | G55: Premium | H55: West
A56: 8 | B56: Daniel King | C56: CUST019 | D56: =SUMIF('Raw Data'!C:C,C56,'Raw Data'!N:N) -> 7309.8 | E56: =COUNTIF('Raw Data'!C:C,C56) -> 7 | F56: =IFERROR(D56/E56,0) -> 1044.2571 | G56: Premium | H56: South
A57: 9 | B57: Lawrence Reed | C57: CUST039 | D57: =SUMIF('Raw Data'!C:C,C57,'Raw Data'!N:N) -> 6989.77 | E57: =COUNTIF('Raw Data'!C:C,C57) -> 8 | F57: =IFERROR(D57/E57,0) -> 873.72125 | G57: Basic | H57: East
A58: 10 | B58: Joseph Jackson | C58: CUST013 | D58: =SUMIF('Raw Data'!C:C,C58,'Raw Data'!N:N) -> 6949.84 | E58: =COUNTIF('Raw Data'!C:C,C58) -> 5 | F58: =IFERROR(D58/E58,0) -> 1389.968 | G58: Premium | H58: South
A61: 🛒 PRODUCT FREQUENCY ANALYSIS
A62: Product | B62: Category | C62: Transactions | D62: Units Sold | E62: Revenue | F62: Avg Unit Price
A63: Laptop | B63: Electronics | C63: =COUNTIF('Raw Data'!F:F,A63) -> 24 | D63: =SUMIF('Raw Data'!F:F,A63,'Raw Data'!H:H) -> 75 | E63: =SUMIF('Raw Data'!F:F,A63,'Raw Data'!N:N) -> 67499.25 | F63: =IFERROR(AVERAGEIF('Raw Data'!F:F,A63,'Raw Data'!I:I),0) -> 899.99
A64: Smartphone | B64: Electronics | C64: =COUNTIF('Raw Data'!F:F,A64) -> 31 | D64: =SUMIF('Raw Data'!F:F,A64,'Raw Data'!H:H) -> 96 | E64: =SUMIF('Raw Data'!F:F,A64,'Raw Data'!N:N) -> 67199.04 | F64: =IFERROR(AVERAGEIF('Raw Data'!F:F,A64,'Raw Data'!I:I),0) -> 699.99
A65: Monitor | B65: Electronics | C65: =COUNTIF('Raw Data'!F:F,A65) -> 26 | D65: =SUMIF('Raw Data'!F:F,A65,'Raw Data'!H:H) -> 88 | E65: =SUMIF('Raw Data'!F:F,A65,'Raw Data'!N:N) -> 21999.12 | F65: =IFERROR(AVERAGEIF('Raw Data'!F:F,A65,'Raw Data'!I:I),0) -> 249.99
A66: Keyboard | B66: Electronics | C66: =COUNTIF('Raw Data'!F:F,A66) -> 34 | D66: =SUMIF('Raw Data'!F:F,A66,'Raw Data'!H:H) -> 89 | E66: =SUMIF('Raw Data'!F:F,A66,'Raw Data'!N:N) -> 8009.11 | F66: =IFERROR(AVERAGEIF('Raw Data'!F:F,A66,'Raw Data'!I:I),0) -> 89.99
A67: Headphones | B67: Electronics | C67: =COUNTIF('Raw Data'!F:F,A67) -> 16 | D67: =SUMIF('Raw Data'!F:F,A67,'Raw Data'!H:H) -> 47 | E67: =SUMIF('Raw Data'!F:F,A67,'Raw Data'!N:N) -> 7049.53 | F67: =IFERROR(AVERAGEIF('Raw Data'!F:F,A67,'Raw Data'!I:I),0) -> 149.99
A68: Blender | B68: Appliances | C68: =COUNTIF('Raw Data'!F:F,A68) -> 29 | D68: =SUMIF('Raw Data'!F:F,A68,'Raw Data'!H:H) -> 87 | E68: =SUMIF('Raw Data'!F:F,A68,'Raw Data'!N:N) -> 5219.13 | F68: =IFERROR(AVERAGEIF('Raw Data'!F:F,A68,'Raw Data'!I:I),0) -> 59.99
A69: Coffee Maker | B69: Appliances | C69: =COUNTIF('Raw Data'!F:F,A69) -> 14 | D69: =SUMIF('Raw Data'!F:F,A69,'Raw Data'!H:H) -> 39 | E69: =SUMIF('Raw Data'!F:F,A69,'Raw Data'!N:N) -> 3119.61 | F69: =IFERROR(AVERAGEIF('Raw Data'!F:F,A69,'Raw Data'!I:I),0) -> 79.99
A70: Bookshelf | B70: Furniture | C70: =COUNTIF('Raw Data'!F:F,A70) -> 35 | D70: =SUMIF('Raw Data'!F:F,A70,'Raw Data'!H:H) -> 102 | E70: =SUMIF('Raw Data'!F:F,A70,'Raw Data'!N:N) -> 15298.98 | F70: =IFERROR(AVERAGEIF('Raw Data'!F:F,A70,'Raw Data'!I:I),0) -> 149.99
A71: Desk | B71: Furniture | C71: =COUNTIF('Raw Data'!F:F,A71) -> 26 | D71: =SUMIF('Raw Data'!F:F,A71,'Raw Data'!H:H) -> 78 | E71: =SUMIF('Raw Data'!F:F,A71,'Raw Data'!N:N) -> 23399.22 | F71: =IFERROR(AVERAGEIF('Raw Data'!F:F,A71,'Raw Data'!I:I),0) -> 299.99
A72: Office Chair | B72: Furniture | C72: =COUNTIF('Raw Data'!F:F,A72) -> 15 | D72: =SUMIF('Raw Data'!F:F,A72,'Raw Data'!H:H) -> 52 | E72: =SUMIF('Raw Data'!F:F,A72,'Raw Data'!N:N) -> 10399.48 | F72: =IFERROR(AVERAGEIF('Raw Data'!F:F,A72,'Raw Data'!I:I),0) -> 199.99
A75: 💳 PAYMENT METHOD ANALYSIS
A76: Payment Method | B76: Transactions | C76: Revenue | D76: Avg Order | E76: % Transactions | F76: % Revenue
A77: Cash | B77: =COUNTIF('Raw Data'!J:J,A77) -> 76 | C77: =SUMIF('Raw Data'!J:J,A77,'Raw Data'!N:N) -> 57427.79 | D77: =IFERROR(C77/B77,0) -> 755.62882 | E77: =IFERROR(B77/SUM(B77:B80),0) -> 0.304 | F77: =IFERROR(C77/SUM(C77:C80),0) -> 0.25056578
A78: Credit Card | B78: =COUNTIF('Raw Data'!J:J,A78) -> 68 | C78: =SUMIF('Raw Data'!J:J,A78,'Raw Data'!N:N) -> 61447.96 | D78: =IFERROR(C78/B78,0) -> 903.64647 | E78: =IFERROR(B78/SUM(B77:B80),0) -> 0.272 | F78: =IFERROR(C78/SUM(C77:C80),0) -> 0.26810636
A79: Debit Card | B79: =COUNTIF('Raw Data'!J:J,A79) -> 54 | C79: =SUMIF('Raw Data'!J:J,A79,'Raw Data'!N:N) -> 52118.31 | D79: =IFERROR(C79/B79,0) -> 965.15389 | E79: =IFERROR(B79/SUM(B77:B80),0) -> 0.216 | F79: =IFERROR(C79/SUM(C77:C80),0) -> 0.22739975
A80: PayPal | B80: =COUNTIF('Raw Data'!J:J,A80) -> 52 | C80: =SUMIF('Raw Data'!J:J,A80,'Raw Data'!N:N) -> 58198.41 | D80: =IFERROR(C80/B80,0) -> 1119.2002 | E80: =IFERROR(B80/SUM(B77:B80),0) -> 0.208 | F80: =IFERROR(C80/SUM(C77:C80),0) -> 0.25392811
A83: 🔍 FILTER FUNCTION DEMO – Premium Electronics
A84: Transaction_ID | B84: Date | C84: Customer | D84: Product | E84: Category | F84: Qty | G84: Unit Price | H84: Total
A85: [See Dashboard tab for full FILTER results via Pivot]
A88: 🔤 ABBREVIATIONS & TEXT FUNCTIONS
A89: Original | B89: UPPER | C89: LOWER | D89: LEFT(3) | E89: Initials | F89: Abbrev (MID)
A90: Electronics | B90: =UPPER(A90) -> ELECTRONICS | C90: =LOWER(A90) -> electronics | D90: =LEFT(A90,3) -> Ele | E90: =LEFT(A90,1)&IF(ISNUMBER(FIND(" ",A90)),MID(A90,FIND(" ",A90)+1,1),"") -> E | F90: =LEFT(A90,1)&MID(A90,FIND(LEFT(A90,1),A90)+1,2) -> Ele
A91: Furniture | B91: =UPPER(A91) -> FURNITURE | C91: =LOWER(A91) -> furniture | D91: =LEFT(A91,3) -> Fur | E91: =LEFT(A91,1)&IF(ISNUMBER(FIND(" ",A91)),MID(A91,FIND(" ",A91)+1,1),"") -> F | F91: =LEFT(A91,1)&MID(A91,FIND(LEFT(A91,1),A91)+1,2) -> Fur
A92: Appliances | B92: =UPPER(A92) -> APPLIANCES | C92: =LOWER(A92) -> appliances | D92: =LEFT(A92,3) -> App | E92: =LEFT(A92,1)&IF(ISNUMBER(FIND(" ",A92)),MID(A92,FIND(" ",A92)+1,1),"") -> A | F92: =LEFT(A92,1)&MID(A92,FIND(LEFT(A92,1),A92)+1,2) -> App
A93: Premium | B93: =UPPER(A93) -> PREMIUM | C93: =LOWER(A93) -> premium | D93: =LEFT(A93,3) -> Pre | E93: =LEFT(A93,1)&IF(ISNUMBER(FIND(" ",A93)),MID(A93,FIND(" ",A93)+1,1),"") -> P | F93: =LEFT(A93,1)&MID(A93,FIND(LEFT(A93,1),A93)+1,2) -> Pre
A94: Standard | B94: =UPPER(A94) -> STANDARD | C94: =LOWER(A94) -> standard | D94: =LEFT(A94,3) -> Sta | E94: =LEFT(A94,1)&IF(ISNUMBER(FIND(" ",A94)),MID(A94,FIND(" ",A94)+1,1),"") -> S | F94: =LEFT(A94,1)&MID(A94,FIND(LEFT(A94,1),A94)+1,2) -> Sta
A95: Basic | B95: =UPPER(A95) -> BASIC | C95: =LOWER(A95) -> basic | D95: =LEFT(A95,3) -> Bas | E95: =LEFT(A95,1)&IF(ISNUMBER(FIND(" ",A95)),MID(A95,FIND(" ",A95)+1,1),"") -> B | F95: =LEFT(A95,1)&MID(A95,FIND(LEFT(A95,1),A95)+1,2) -> Bas
A96: Credit Card | B96: =UPPER(A96) -> CREDIT CARD | C96: =LOWER(A96) -> credit card | D96: =LEFT(A96,3) -> Cre | E96: =LEFT(A96,1)&IF(ISNUMBER(FIND(" ",A96)),MID(A96,FIND(" ",A96)+1,1),"") -> CC | F96: =LEFT(A96,1)&MID(A96,FIND(LEFT(A96,1),A96)+1,2) -> Cre
A97: Debit Card | B97: =UPPER(A97) -> DEBIT CARD | C97: =LOWER(A97) -> debit card | D97: =LEFT(A97,3) -> Deb | E97: =LEFT(A97,1)&IF(ISNUMBER(FIND(" ",A97)),MID(A97,FIND(" ",A97)+1,1),"") -> DC | F97: =LEFT(A97,1)&MID(A97,FIND(LEFT(A97,1),A97)+1,2) -> Deb
A98: Monitor | B98: =UPPER(A98) -> MONITOR | C98: =LOWER(A98) -> monitor | D98: =LEFT(A98,3) -> Mon | E98: =LEFT(A98,1)&IF(ISNUMBER(FIND(" ",A98)),MID(A98,FIND(" ",A98)+1,1),"") -> M | F98: =LEFT(A98,1)&MID(A98,FIND(LEFT(A98,1),A98)+1,2) -> Mon
A99: Smartphone | B99: =UPPER(A99) -> SMARTPHONE | C99: =LOWER(A99) -> smartphone | D99: =LEFT(A99,3) -> Sma | E99: =LEFT(A99,1)&IF(ISNUMBER(FIND(" ",A99)),MID(A99,FIND(" ",A99)+1,1),"") -> S | F99: =LEFT(A99,1)&MID(A99,FIND(LEFT(A99,1),A99)+1,2) -> Sma
A102: 🔗 COMPARE LISTS – Premium vs Basic Customers
A103: Premium Customers | B103: ID | D103: Basic Customers | E103: ID | F103: Match Found?
A104: Joseph Jackson | B104: CUST013 | D104: Paul Baker | E104: CUST023 | F104: =IF(ISNUMBER(MATCH(B104,E104:E113,0)),"✅ Match","❌ No Match") -> ❌ No Match
A105: Kathleen Bennett | B105: CUST046 | D105: Charles Allen | E105: CUST017 | F105: =IF(ISNUMBER(MATCH(B105,E104:E113,0)),"✅ Match","❌ No Match") -> ✅ Match
A106: Michael Brown | B106: CUST003 | D106: Kathleen Bennett | E106: CUST046 | F106: =IF(ISNUMBER(MATCH(B106,E104:E113,0)),"✅ Match","❌ No Match") -> ❌ No Match
A107: Karen Hill | B107: CUST026 | D107: Michelle Rogers | E107: CUST038 | F107: =IF(ISNUMBER(MATCH(B107,E104:E113,0)),"✅ Match","❌ No Match") -> ❌ No Match
A108: Peter Richardson | B108: CUST041 | D108: Maria Garcia | E108: CUST010 | F108: =IF(ISNUMBER(MATCH(B108,E104:E113,0)),"✅ Match","❌ No Match") -> ❌ No Match
A109: Mark Carter | B109: CUST025 | D109: Barbara Young | E109: CUST018 | F109: =IF(ISNUMBER(MATCH(B109,E104:E113,0)),"✅ Match","❌ No Match") -> ❌ No Match
A110: Virginia Sanders | B110: CUST048 | D110: Susan Green | E110: CUST022 | F110: =IF(ISNUMBER(MATCH(B110,E104:E113,0)),"✅ Match","❌ No Match") -> ❌ No Match
A111: Linda Martin | B111: CUST014 | D111: Lisa Anderson | E111: CUST006 | F111: =IF(ISNUMBER(MATCH(B111,E104:E113,0)),"✅ Match","❌ No Match") -> ❌ No Match
A112: Patricia Moore | B112: CUST012 | D112: Patricia Moore | E112: CUST012 | F112: =IF(ISNUMBER(MATCH(B112,E104:E113,0)),"✅ Match","❌ No Match") -> ✅ Match
A113: Emma Wilson | B113: CUST002 | D113: Sharon Butler | E113: CUST040 | F113: =IF(ISNUMBER(MATCH(B113,E104:E113,0)),"✅ Match","❌ No Match") -> ❌ No Match
A116: 📐 WHAT-IF ANALYSIS – Scenario Manager
A117: Scenario | B117: Price Multiplier | C117: Qty Multiplier | D117: Projected Revenue | E117: Change vs Base | F117: % Change
A118: Base | B118: 1 | C118: 1 | D118: =SUM('Raw Data'!N2:N10000) -> 229192.47 | E118: 0 | F118: 0
A119: Optimistic | B119: 1.1 | C119: 1.15 | D119: =D118*B119*C119 -> 289928.47 | E119: =D119-D118 -> 60736.005 | F119: =IFERROR((D119-D118)/D118,0) -> 0.265
A120: Moderate | B120: 1.05 | C120: 1.05 | D120: =D118*B120*C120 -> 252684.7 | E120: =D120-D118 -> 23492.228 | F120: =IFERROR((D120-D118)/D118,0) -> 0.1025
A121: Pessimistic | B121: 0.9 | C121: 0.85 | D121: =D118*B121*C121 -> 175332.24 | E121: =D121-D118 -> -53860.23 | F121: =IFERROR((D121-D118)/D118,0) -> -0.235
...

Sheet Visualizations
A1: 📊 CUSTOMER TRANSACTION VISUALIZATIONS & CHARTS
N7: Category | O7: Revenue
N8: Electronics | O8: =SUMIF('Raw Data'!G:G,N8,'Raw Data'!N:N) -> 171756.05
N9: Furniture | O9: =SUMIF('Raw Data'!G:G,N9,'Raw Data'!N:N) -> 49097.68
N10: Appliances | O10: =SUMIF('Raw Data'!G:G,N10,'Raw Data'!N:N) -> 8338.74
N21: Region | O21: Revenue
N22: Central | O22: =SUMIF('Raw Data'!K:K,N22,'Raw Data'!N:N) -> 41288.34
N23: East | O23: =SUMIF('Raw Data'!K:K,N23,'Raw Data'!N:N) -> 59288.39
N24: North | O24: =SUMIF('Raw Data'!K:K,N24,'Raw Data'!N:N) -> 50808.31
N25: South | O25: =SUMIF('Raw Data'!K:K,N25,'Raw Data'!N:N) -> 36398.75
N26: West | O26: =SUMIF('Raw Data'!K:K,N26,'Raw Data'!N:N) -> 41408.68
A30: Product | B30: Revenue
A31: Laptop | B31: =SUMIF('Raw Data'!F:F,A31,'Raw Data'!N:N) -> 67499.25
A32: Smartphone | B32: =SUMIF('Raw Data'!F:F,A32,'Raw Data'!N:N) -> 67199.04
A33: Desk | B33: =SUMIF('Raw Data'!F:F,A33,'Raw Data'!N:N) -> 23399.22
A34: Monitor | B34: =SUMIF('Raw Data'!F:F,A34,'Raw Data'!N:N) -> 21999.12
A35: Bookshelf | B35: =SUMIF('Raw Data'!F:F,A35,'Raw Data'!N:N) -> 15298.98
C38: Trend
C39: =IFERROR(FORECAST(1,B$59:B$71,ROW(INDIRECT("1:13"))),0) -> 19160.461
C40: =IFERROR(FORECAST(2,B$59:B$71,ROW(INDIRECT("1:13"))),0) -> 18905.416
C41: =IFERROR(FORECAST(3,B$59:B$71,ROW(INDIRECT("1:13"))),0) -> 18650.37
C42: =IFERROR(FORECAST(4,B$59:B$71,ROW(INDIRECT("1:13"))),0) -> 18395.325
C43: =IFERROR(FORECAST(5,B$59:B$71,ROW(INDIRECT("1:13"))),0) -> 18140.28
C44: =IFERROR(FORECAST(6,B$59:B$71,ROW(INDIRECT("1:13"))),0) -> 17885.235
C45: =IFERROR(FORECAST(7,B$59:B$71,ROW(INDIRECT("1:13"))),0) -> 17630.19
C46: =IFERROR(FORECAST(8,B$59:B$71,ROW(INDIRECT("1:13"))),0) -> 17375.145
C47: =IFERROR(FORECAST(9,B$59:B$71,ROW(INDIRECT("1:13"))),0) -> 17120.1
C48: =IFERROR(FORECAST(10,B$59:B$71,ROW(INDIRECT("1:13"))),0) -> 16865.055
C49: =IFERROR(FORECAST(11,B$59:B$71,ROW(INDIRECT("1:13"))),0) -> 16610.01
C50: =IFERROR(FORECAST(12,B$59:B$71,ROW(INDIRECT("1:13"))),0) -> 16354.964
C51: =IFERROR(FORECAST(13,B$59:B$71,ROW(INDIRECT("1:13"))),0) -> 16099.919
A58: Month | B58: Revenue
A59: 2024-04 | B59: 20919.33
A60: 2024-05 | B60: 17039.35
A61: 2024-06 | B61: 19299.45
A62: 2024-07 | B62: 18479.4
A63: 2024-08 | B63: 15759.43
A64: 2024-09 | B64: 12989.51
A65: 2024-10 | B65: 20609.52
A66: 2024-11 | B66: 12309.44
A67: 2024-12 | B67: 23039.3
A68: 2025-01 | B68: 25799.15
A69: 2025-02 | B69: 16069.38
A70: 2025-03 | B70: 19899.38
A71: 2025-04 | B71: 6979.83

Sheet Dashboard
A1: 🏪 CUSTOMER TRANSACTIONS ANALYTICS DASHBOARD
A3: 💰 TOTAL REVENUE | G3: 📦 TRANSACTIONS | M3: 👤 CUSTOMERS | S3: 🛍️ AVG ORDER
A4: =SUM('Raw Data'!N2:N10000) -> 229192.47 | G4: =COUNTA('Raw Data'!A2:A10000) -> 250 | M4: =SUMPRODUCT(1/COUNTIF('Raw Data'!C2:C251,'Raw Data'!C2:C251)) -> 50 | S4: =IFERROR(AVERAGE('Raw Data'!N2:N10000),0) -> 916.76988
A7: 📊 UNITS SOLD | G7: 🏆 TOP PRODUCT | M7: 🌍 TOP REGION | S7: 💳 TOP PAYMENT
A8: =SUM('Raw Data'!H2:H10000) -> 753 | G8: =INDEX('Raw Data'!F:F,MATCH(LARGE(COUNTIF('Raw Data'!F2:F251,'Raw Data'!F2:F251),1),COUNTIF('Raw Data'!F2:F251,'Raw Data'!F2:F251),0)+1) -> #N/A | M8: =INDEX('Raw Data'!K:K,MATCH(LARGE(COUNTIF('Raw Data'!K2:K251,'Raw Data'!K2:K251),1),COUNTIF('Raw Data'!K2:K251,'Raw Data'!K2:K251),0)+1) -> #N/A | S8: =INDEX('Raw Data'!J:J,MATCH(LARGE(COUNTIF('Raw Data'!J2:J251,'Raw Data'!J2:J251),1),COUNTIF('Raw Data'!J2:J251,'Raw Data'!J2:J251),0)+1) -> #N/A
A12: 📋 CATEGORY PERFORMANCE | H12: 🌍 REGIONAL PERFORMANCE | O12: 👥 SEGMENT PERFORMANCE
A13: Category | B13: Revenue | C13: Txns | D13: Units | E13: Avg Order | F13: % Share | H13: Region | I13: Revenue | J13: Txns | K13: Units | L13: Avg Order | M13: % Share | O13: Segment | P13: Revenue | Q13: Txns | R13: Avg Order | S13: % Rev | T13: KPI
A14: Electronics | B14: =SUMIF('Raw Data'!G:G,A14,'Raw Data'!N:N) -> 171756.05 | C14: =COUNTIF('Raw Data'!G:G,A14) -> 131 | D14: =SUMIF('Raw Data'!G:G,A14,'Raw Data'!H:H) -> 395 | E14: =IFERROR(B14/C14,0) -> 1311.1149 | F14: =IFERROR(B14/SUM(B14:B16),0) -> 0.74939657 | H14: Central | I14: =SUMIF('Raw Data'!K:K,H14,'Raw Data'!N:N) -> 41288.34 | J14: =COUNTIF('Raw Data'!K:K,H14) -> 54 | K14: =SUMIF('Raw Data'!K:K,H14,'Raw Data'!H:H) -> 166 | L14: =IFERROR(I14/J14,0) -> 764.59889 | M14: =IFERROR(I14/SUM(I14:I18),0) -> 0.18014702 | O14: Basic | P14: =SUMIF('Raw Data'!L:L,O14,'Raw Data'!N:N) -> 62177.81 | Q14: =COUNTIF('Raw Data'!L:L,O14) -> 74 | R14: =IFERROR(P14/Q14,0) -> 840.24068 | S14: =IFERROR(P14/SUM(P14:P16),0) -> 0.27129081 | T14: =IF(P14=MAX(P14:P16),"🥇 Leader",IF(P14=MIN(P14:P16),"⚠️ Lowest","✅ Mid")) -> ⚠️ Lowest
A15: Furniture | B15: =SUMIF('Raw Data'!G:G,A15,'Raw Data'!N:N) -> 49097.68 | C15: =COUNTIF('Raw Data'!G:G,A15) -> 76 | D15: =SUMIF('Raw Data'!G:G,A15,'Raw Data'!H:H) -> 232 | E15: =IFERROR(B15/C15,0) -> 646.02211 | F15: =IFERROR(B15/SUM(B14:B16),0) -> 0.2142203 | H15: East | I15: =SUMIF('Raw Data'!K:K,H15,'Raw Data'!N:N) -> 59288.39 | J15: =COUNTIF('Raw Data'!K:K,H15) -> 48 | K15: =SUMIF('Raw Data'!K:K,H15,'Raw Data'!H:H) -> 161 | L15: =IFERROR(I15/J15,0) -> 1235.1748 | M15: =IFERROR(I15/SUM(I14:I18),0) -> 0.25868385 | O15: Premium | P15: =SUMIF('Raw Data'!L:L,O15,'Raw Data'!N:N) -> 84657.12 | Q15: =COUNTIF('Raw Data'!L:L,O15) -> 95 | R15: =IFERROR(P15/Q15,0) -> 891.12758 | S15: =IFERROR(P15/SUM(P14:P16),0) -> 0.3693713 | T15: =IF(P15=MAX(P14:P16),"🥇 Leader",IF(P15=MIN(P14:P16),"⚠️ Lowest","✅ Mid")) -> 🥇 Leader
A16: Appliances | B16: =SUMIF('Raw Data'!G:G,A16,'Raw Data'!N:N) -> 8338.74 | C16: =COUNTIF('Raw Data'!G:G,A16) -> 43 | D16: =SUMIF('Raw Data'!G:G,A16,'Raw Data'!H:H) -> 126 | E16: =IFERROR(B16/C16,0) -> 193.92419 | F16: =IFERROR(B16/SUM(B14:B16),0) -> 0.036383132 | H16: North | I16: =SUMIF('Raw Data'!K:K,H16,'Raw Data'!N:N) -> 50808.31 | J16: =COUNTIF('Raw Data'!K:K,H16) -> 59 | K16: =SUMIF('Raw Data'!K:K,H16,'Raw Data'!H:H) -> 169 | L16: =IFERROR(I16/J16,0) -> 861.1578 | M16: =IFERROR(I16/SUM(I14:I18),0) -> 0.22168403 | O16: Standard | P16: =SUMIF('Raw Data'!L:L,O16,'Raw Data'!N:N) -> 82357.54 | Q16: =COUNTIF('Raw Data'!L:L,O16) -> 81 | R16: =IFERROR(P16/Q16,0) -> 1016.7598 | S16: =IFERROR(P16/SUM(P14:P16),0) -> 0.3593379 | T16: =IF(P16=MAX(P14:P16),"🥇 Leader",IF(P16=MIN(P14:P16),"⚠️ Lowest","✅ Mid")) -> ✅ Mid
H17: South | I17: =SUMIF('Raw Data'!K:K,H17,'Raw Data'!N:N) -> 36398.75 | J17: =COUNTIF('Raw Data'!K:K,H17) -> 42 | K17: =SUMIF('Raw Data'!K:K,H17,'Raw Data'!H:H) -> 125 | L17: =IFERROR(I17/J17,0) -> 866.6369 | M17: =IFERROR(I17/SUM(I14:I18),0) -> 0.15881303
H18: West | I18: =SUMIF('Raw Data'!K:K,H18,'Raw Data'!N:N) -> 41408.68 | J18: =COUNTIF('Raw Data'!K:K,H18) -> 47 | K18: =SUMIF('Raw Data'!K:K,H18,'Raw Data'!H:H) -> 132 | L18: =IFERROR(I18/J18,0) -> 881.03574 | M18: =IFERROR(I18/SUM(I14:I18),0) -> 0.18067208
A20: 🏆 TOP 5 CUSTOMERS | I20: 💳 PAYMENT METHODS | O20: 📅 MONTHLY REVENUE
A21: Rank | B21: Customer | C21: ID | D21: Revenue | E21: Txns | F21: Segment | G21: Status | I21: Payment | J21: Txns | K21: Revenue | L21: Avg | M21: % Rev | O21: Month | P21: Revenue | Q21: YoY Chg | R21: Trend
A22: 1 | B22: Mark Carter | C22: CUST025 | D22: =SUMIF('Raw Data'!C:C,C22,'Raw Data'!N:N) -> 15659.65 | E22: =COUNTIF('Raw Data'!C:C,C22) -> 12 | F22: Standard | G22: ⭐ High Value | I22: Cash | J22: =COUNTIF('Raw Data'!J:J,I22) -> 76 | K22: =SUMIF('Raw Data'!J:J,I22,'Raw Data'!N:N) -> 57427.79 | L22: =IFERROR(K22/J22,0) -> 755.62882 | M22: =IFERROR(K22/SUM(K22:K25),0) -> 0.25056578 | O22: 2024-04 | P22: 20919.33 | Q22: — | R22: 📊
A23: 2 | B23: Edward Mitchell | C23: CUST029 | D23: =SUMIF('Raw Data'!C:C,C23,'Raw Data'!N:N) -> 11919.77 | E23: =COUNTIF('Raw Data'!C:C,C23) -> 6 | F23: Standard | G23: ⭐ High Value | I23: Credit Card | J23: =COUNTIF('Raw Data'!J:J,I23) -> 68 | K23: =SUMIF('Raw Data'!J:J,I23,'Raw Data'!N:N) -> 61447.96 | L23: =IFERROR(K23/J23,0) -> 903.64647 | M23: =IFERROR(K23/SUM(K22:K25),0) -> 0.26810636 | O23: 2024-05 | P23: 17039.35 | Q23: =IFERROR((P23-P22)/P22,0) -> -0.18547344 | R23: =IF(P23>P22,"📈","📉") -> 📉
A24: 3 | B24: Barbara Young | C24: CUST018 | D24: =SUMIF('Raw Data'!C:C,C24,'Raw Data'!N:N) -> 10649.8 | E24: =COUNTIF('Raw Data'!C:C,C24) -> 5 | F24: Standard | G24: ⭐ High Value | I24: Debit Card | J24: =COUNTIF('Raw Data'!J:J,I24) -> 54 | K24: =SUMIF('Raw Data'!J:J,I24,'Raw Data'!N:N) -> 52118.31 | L24: =IFERROR(K24/J24,0) -> 965.15389 | M24: =IFERROR(K24/SUM(K22:K25),0) -> 0.22739975 | O24: 2024-06 | P24: 19299.45 | Q24: =IFERROR((P24-P23)/P23,0) -> 0.13264004 | R24: =IF(P24>P23,"📈","📉") -> 📈
A25: 4 | B25: Patricia Moore | C25: CUST012 | D25: =SUMIF('Raw Data'!C:C,C25,'Raw Data'!N:N) -> 9799.73 | E25: =COUNTIF('Raw Data'!C:C,C25) -> 8 | F25: Standard | G25: ⭐ High Value | I25: PayPal | J25: =COUNTIF('Raw Data'!J:J,I25) -> 52 | K25: =SUMIF('Raw Data'!J:J,I25,'Raw Data'!N:N) -> 58198.41 | L25: =IFERROR(K25/J25,0) -> 1119.2002 | M25: =IFERROR(K25/SUM(K22:K25),0) -> 0.25392811 | O25: 2024-07 | P25: 18479.4 | Q25: =IFERROR((P25-P24)/P24,0) -> -0.042490848 | R25: =IF(P25>P24,"📈","📉") -> 📉
A26: 5 | B26: Paul Baker | C26: CUST023 | D26: =SUMIF('Raw Data'!C:C,C26,'Raw Data'!N:N) -> 8309.74 | E26: =COUNTIF('Raw Data'!C:C,C26) -> 8 | F26: Premium | G26: ⭐ High Value | O26: 2024-08 | P26: 15759.43 | Q26: =IFERROR((P26-P25)/P25,0) -> -0.1471893 | R26: =IF(P26>P25,"📈","📉") -> 📉
O27: 2024-09 | P27: 12989.51 | Q27: =IFERROR((P27-P26)/P26,0) -> -0.1757627 | R27: =IF(P27>P26,"📈","📉") -> 📉
O28: 2024-10 | P28: 20609.52 | Q28: =IFERROR((P28-P27)/P27,0) -> 0.58662798 | R28: =IF(P28>P27,"📈","📉") -> 📈
O29: 2024-11 | P29: 12309.44 | Q29: =IFERROR((P29-P28)/P28,0) -> -0.40273039 | R29: =IF(P29>P28,"📈","📉") -> 📉
O30: 2024-12 | P30: 23039.3 | Q30: =IFERROR((P30-P29)/P29,0) -> 0.87167735 | R30: =IF(P30>P29,"📈","📉") -> 📈
O31: 2025-01 | P31: 25799.15 | Q31: =IFERROR((P31-P30)/P30,0) -> 0.1197888 | R31: =IF(P31>P30,"📈","📉") -> 📈
O32: 2025-02 | P32: 16069.38 | Q32: =IFERROR((P32-P31)/P31,0) -> -0.37713529 | R32: =IF(P32>P31,"📈","📉") -> 📉
O33: 2025-03 | P33: 19899.38 | Q33: =IFERROR((P33-P32)/P32,0) -> 0.23834149 | R33: =IF(P33>P32,"📈","📉") -> 📈
O34: 2025-04 | P34: 6979.83 | Q34: =IFERROR((P34-P33)/P33,0) -> -0.64924385 | R34: =IF(P34>P33,"📈","📉") -> 📉

Sheet Insights Report
A1: 📋 BUSINESS INSIGHTS REPORT – CUSTOMER TRANSACTION ANALYSIS 2024-2025
A2: =CONCATENATE("Report Generated: ",TEXT(TODAY(),"DD-MMM-YYYY")," | Data Period: Apr 2024 – Apr 2025") -> Report Generated: 29-Mar-2026 | Data Period: Apr 2024 – Apr 2025
A4: 📌 EXECUTIVE SUMMARY
A5: This report analyzes 250 customer transactions from April 2024 to April 2025, covering 50+ unique customers across 5 regions.
A6: Total Revenue tracked: =CONCATENATE("$",TEXT(SUM('Raw Data'!N2:N10000),"#,##0.00"))
A7: The dataset covers 3 product categories (Electronics, Furniture, Appliances) with 10 distinct products.
A8: Insights are derived using Excel's SUMIF, COUNTIF, AVERAGEIF, FILTER concepts, DATEDIF, and statistical functions.
A10: 🔍 KEY FINDINGS
A11: ✅ 1. Electronics Dominance
A12: → Electronics is the highest revenue-generating category, driven by Laptops and Smartphones — the two most expensive products.
A14: ✅ 2. Premium Customers Drive Revenue
A15: → Premium customer segment contributes the highest revenue despite having fewer transactions than Standard, indicating higher average order values.
A17: ✅ 3. Regional Concentration
A18: → North and West regions show the highest transaction volumes. Targeted marketing in South and Central could unlock growth.
... A59: 7. Monitor monthly revenue trend and flag any deviation from the regression forecast as an early warning signal.
