Workbook
Name NativeTimeline_Date: #N/A
Name NativeTimeline_Date1: #N/A
Name Slicer_Category: #N/A
Name Slicer_Payment_Method: #N/A
Name Slicer_Region: #N/A

Sheet RawData
A1: Transaction_ID | B1: Date | C1: Customer_ID | D1: Customer_Name | E1: Product_ID | F1: Product_Name | G1: Category | H1: Quantity | I1: Unit_Price | J1: Payment_Method | K1: Region | L1: Customer_Segment | M1: Customer_Since | N1: Total_Amount | O1: Column1 | P1: Filter Data according Region
A2: TRX0155 | B2: 45393 | C2: CUST023 | D2: Paul Baker | E2: P009 | F2: Monitor | G2: Electronics | H2: 3 | I2: 249.99 | J2: Cash | K2: Central | L2: Basic | M2: 44425 | N2: 749.97 | P2: Transaction_ID | Q2: Date | R2: Customer_ID | S2: Customer_Name | T2: Product_ID | U2: Product_Name | V2: Category | W2: Quantity | X2: Unit_Price | Y2: Payment_Method | Z2: Region | AA2: Customer_Segment | AB2: Customer_Since | AC2: Total_Amount
A3: TRX0023 | B3: 45396 | C3: CUST013 | D3: Joseph Jackson | E3: P009 | F3: Monitor | G3: Electronics | H3: 3 | I3: 249.99 | J3: Credit Card | K3: Central | L3: Premium | M3: 44575 | N3: 749.97 | P3: {=_xlfn._xlws.FILTER(A2:N252,K2:K252="West","Not Found")} -> TRX0092 | Q3: 45403 | R3: CUST024 | S3: Dorothy Nelson | T3: P005 | U3: Blender | V3: Appliances | W3: 2 | X3: 59.99 | Y3: Cash | Z3: West | AA3: Standard | AB3: 44746 | AC3: 119.98
A4: TRX0139 | B4: 45399 | C4: CUST021 | D4: Kevin Scott | E4: P005 | F4: Blender | G4: Appliances | H4: 3 | I4: 59.99 | J4: PayPal | K4: South | L4: Standard | M4: 45262 | N4: 179.97 | P4: TRX0185 | Q4: 45408 | R4: CUST026 | S4: Karen Hill | T4: P005 | U4: Blender | V4: Appliances | W4: 3 | X4: 59.99 | Y4: Cash | Z4: West | AA4: Premium | AB4: 45207 | AC4: 179.97
A5: TRX0043 | B5: 45400 | C5: CUST046 | D5: Kathleen Bennett | E5: P005 | F5: Blender | G5: Appliances | H5: 3 | I5: 59.99 | J5: Cash | K5: North | L5: Premium | M5: 45114 | N5: 179.97 | P5: TRX0138 | Q5: 45408 | R5: CUST022 | S5: Susan Green | T5: P008 | U5: Bookshelf | V5: Furniture | W5: 1 | X5: 149.99 | Y5: Credit Card | Z5: West | AA5: Standard | AB5: 45103 | AC5: 149.99
A6: TRX0212 | B6: 45400 | C6: CUST003 | D6: Michael Brown | E6: P008 | F6: Bookshelf | G6: Furniture | H6: 5 | I6: 149.99 | J6: Credit Card | K6: North | L6: Premium | M6: 45295 | N6: 749.95 | P6: TRX0191 | Q6: 45409 | R6: CUST038 | S6: Michelle Rogers | T6: P002 | U6: Smartphone | V6: Electronics | W6: 3 | X6: 699.99 | Y6: Credit Card | Z6: West | AA6: Basic | AB6: 44577 | AC6: 2099.97
A7: TRX0092 | B7: 45403 | C7: CUST024 | D7: Dorothy Nelson | E7: P005 | F7: Blender | G7: Appliances | H7: 2 | I7: 59.99 | J7: Cash | K7: West | L7: Standard | M7: 44746 | N7: 119.98 | P7: TRX0122 | Q7: 45410 | R7: CUST025 | S7: Mark Carter | T7: P001 | U7: Laptop | V7: Electronics | W7: 4 | X7: 899.99 | Y7: Credit Card | Z7: West | AA7: Standard | AB7: 45327 | AC7: 3599.96
A8: TRX0193 | B8: 45403 | C8: CUST024 | D8: Dorothy Nelson | E8: P003 | F8: Headphones | G8: Electronics | H8: 5 | I8: 149.99 | J8: Credit Card | K8: Central | L8: Standard | M8: 44418 | N8: 749.95 | P8: TRX0231 | Q8: 45412 | R8: CUST018 | S8: Barbara Young | T8: P002 | U8: Smartphone | V8: Electronics | W8: 5 | X8: 699.99 | Y8: Cash | Z8: West | AA8: Basic | AB8: 45167 | AC8: 3499.95
A9: TRX0240 | B9: 45403 | C9: CUST017 | D9: Charles Allen | E9: P005 | F9: Blender | G9: Appliances | H9: 3 | I9: 59.99 | J9: Debit Card | K9: South | L9: Basic | M9: 45007 | N9: 179.97 | P9: TRX0242 | Q9: 45416 | R9: CUST025 | S9: Mark Carter | T9: P007 | U9: Desk | V9: Furniture | W9: 4 | X9: 299.99 | Y9: Cash | Z9: West | AA9: Premium | AB9: 44716 | AC9: 1199.96
A10: TRX0135 | B10: 45405 | C10: CUST009 | D10: Robert Thomas | E10: P001 | F10: Laptop | G10: Electronics | H10: 3 | I10: 899.99 | J10: PayPal | K10: East | L10: Standard | M10: 45299 | N10: 2699.97 | P10: TRX0071 | Q10: 45422 | R10: CUST036 | S10: Nancy Collins | T10: P009 | U10: Monitor | V10: Electronics | W10: 5 | X10: 249.99 | Y10: Credit Card | Z10: West | AA10: Standard | AB10: 44525 | AC10: 1249.95
A11: TRX0185 | B11: 45408 | C11: CUST026 | D11: Karen Hill | E11: P005 | F11: Blender | G11: Appliances | H11: 3 | I11: 59.99 | J11: Cash | K11: West | L11: Premium | M11: 45207 | N11: 179.97 | P11: TRX0194 | Q11: 45428 | R11: CUST006 | S11: Lisa Anderson | T11: P008 | U11: Bookshelf | V11: Furniture | W11: 2 | X11: 149.99 | Y11: Credit Card | Z11: West | AA11: Basic | AB11: 44823 | AC11: 299.98
A12: TRX0138 | B12: 45408 | C12: CUST022 | D12: Susan Green | E12: P008 | F12: Bookshelf | G12: Furniture | H12: 1 | I12: 149.99 | J12: Credit Card | K12: West | L12: Standard | M12: 45103 | N12: 149.99 | P12: TRX0130 | Q12: 45430 | R12: CUST002 | S12: Emma Wilson | T12: P008 | U12: Bookshelf | V12: Furniture | W12: 3 | X12: 149.99 | Y12: Credit Card | Z12: West | AA12: Premium | AB12: 45068 | AC12: 449.97
A13: TRX0209 | B13: 45408 | C13: CUST046 | D13: Kathleen Bennett | E13: P008 | F13: Bookshelf | G13: Furniture | H13: 5 | I13: 149.99 | J13: Debit Card | K13: North | L13: Basic | M13: 44830 | N13: 749.95 | P13: TRX0041 | Q13: 45432 | R13: CUST021 | S13: Kevin Scott | T13: P001 | U13: Laptop | V13: Electronics | W13: 1 | X13: 899.99 | Y13: Credit Card | Z13: West | AA13: Premium | AB13: 44578 | AC13: 899.99
A14: TRX0246 | B14: 45408 | C14: CUST041 | D14: Peter Richardson | E14: P008 | F14: Bookshelf | G14: Furniture | H14: 3 | I14: 149.99 | J14: Cash | K14: North | L14: Premium | M14: 44806 | N14: 449.97 | P14: TRX0015 | Q14: 45440 | R14: CUST008 | S14: Jennifer Taylor | T14: P002 | U14: Smartphone | V14: Electronics | W14: 5 | X14: 699.99 | Y14: PayPal | Z14: West | AA14: Standard | AB14: 44407 | AC14: 3499.95
A15: TRX0067 | B15: 45409 | C15: CUST043 | D15: Dennis Gray | E15: P005 | F15: Blender | G15: Appliances | H15: 3 | I15: 59.99 | J15: Credit Card | K15: North | L15: Standard | M15: 45351 | N15: 179.97 | P15: TRX0128 | Q15: 45444 | R15: CUST040 | S15: Sharon Butler | T15: P005 | U15: Blender | V15: Appliances | W15: 2 | X15: 59.99 | Y15: Cash | Z15: West | AA15: Basic | AB15: 45390 | AC15: 119.98
... A49: TRX0088 | B49: 45456 | C49: CUST006 | D49: Lisa Anderson | E49: P010 | F49: Keyboard | G49: Electronics | H49: 5 | I49: 89.99 | J49: Cash | K49: Central | L49: Premium | M49: 44579 | N49: 449.95 | P49: TRX0250 | Q49: 45746 | R49: CUST026 | S49: Karen Hill | T49: P010 | U49: Keyboard | V49: Electronics | W49: 2 | X49: 89.99 | Y49: Debit Card | Z49: West | AA49: Premium | AB49: 44522 | AC49: 179.98
A50: TRX0115 | B50: 45459 | C50: CUST012 | D50: Patricia Moore | E50: P010 | F50: Keyboard | G50: Electronics | H50: 2 | I50: 89.99 | J50: Credit Card | K50: South | L50: Premium | M50: 44471 | N50: 179.98
A51: TRX0154 | B51: 45459 | C51: CUST023 | D51: Paul Baker | E51: P001 | F51: Laptop | G51: Electronics | H51: 5 | I51: 899.99 | J51: Credit Card | K51: South | L51: Standard | M51: 44974 | N51: 4499.95
A52: TRX0044 | B52: 45459 | C52: CUST029 | D52: Edward Mitchell | E52: P001 | F52: Laptop | G52: Electronics | H52: 5 | I52: 899.99 | J52: PayPal | K52: East | L52: Premium | M52: 45278 | N52: 4499.95
A53: TRX0061 | B53: 45460 | C53: CUST028 | D53: Betty Campbell | E53: P005 | F53: Blender | G53: Appliances | H53: 1 | I53: 59.99 | J53: Debit Card | K53: West | L53: Premium | M53: 45190 | N53: 59.99
A54: TRX0150 | B54: 45460 | C54: CUST008 | D54: Jennifer Taylor | E54: P007 | F54: Desk | G54: Furniture | H54: 2 | I54: 299.99 | J54: Debit Card | K54: East | L54: Standard | M54: 45253 | N54: 599.98
A55: TRX0025 | B55: 45468 | C55: CUST049 | D55: Raymond Ross | E55: P010 | F55: Keyboard | G55: Electronics | H55: 4 | I55: 89.99 | J55: Debit Card | K55: South | L55: Basic | M55: 45281 | N55: 359.96
A56: TRX0078 | B56: 45469 | C56: CUST021 | D56: Kevin Scott | E56: P004 | F56: Coffee Maker | G56: Appliances | H56: 1 | I56: 79.99 | J56: PayPal | K56: Central | L56: Premium | M56: 45352 | N56: 79.99
A57: TRX0007 | B57: 45469 | C57: CUST009 | D57: Robert Thomas | E57: P010 | F57: Keyboard | G57: Electronics | H57: 2 | I57: 89.99 | J57: Cash | K57: West | L57: Basic | M57: 44438 | N57: 179.98
A58: TRX0184 | B58: 45471 | C58: CUST046 | D58: Kathleen Bennett | E58: P002 | F58: Smartphone | G58: Electronics | H58: 3 | I58: 699.99 | J58: Credit Card | K58: East | L58: Premium | M58: 45102 | N58: 2099.97
A59: TRX0104 | B59: 45471 | C59: CUST012 | D59: Patricia Moore | E59: P001 | F59: Laptop | G59: Electronics | H59: 4 | I59: 899.99 | J59: Credit Card | K59: East | L59: Premium | M59: 44993 | N59: 3599.96
A60: TRX0127 | B60: 45472 | C60: CUST030 | D60: Helen Roberts | E60: P008 | F60: Bookshelf | G60: Furniture | H60: 1 | I60: 149.99 | J60: PayPal | K60: East | L60: Basic | M60: 44851 | N60: 149.99
A61: TRX0096 | B61: 45474 | C61: CUST002 | D61: Emma Wilson | E61: P010 | F61: Keyboard | G61: Electronics | H61: 2 | I61: 89.99 | J61: PayPal | K61: Central | L61: Premium | M61: 45275 | N61: 179.98
... A251: TRX0064 | B251: 45758 | C251: CUST031 | D251: Steven Turner | E251: P010 | F251: Keyboard | G251: Electronics | H251: 3 | I251: 89.99 | J251: Debit Card | K251: North | L251: Premium | M251: 44878 | N251: 269.97

Sheet BasicTask
A1: ToDay | B1: Now | C1: DOB | D1: DateDif | E1: EOMONTH | F1: Timestamp
A2: =TODAY() -> 46122 | B2: =NOW() -> 46122.997 | C2: 38225 | D2: =DATEDIF(Table3[[#This Row],[DOB]],TODAY(),"Y") -> 21 | E2: =EOMONTH(Table3[[#This Row],[DOB]],3) -> 38321 | F2: =IF(A2<>"",IF(F2="",NOW(),F2),"") -> 0
A3: =TODAY() -> 46122 | B3: =NOW() -> 46122.997 | C3: 38955 | D3: =DATEDIF(Table3[[#This Row],[DOB]],TODAY(),"Y") -> 19 | E3: =EOMONTH(Table3[[#This Row],[DOB]],3) -> 39051 | F3: =IF(A3<>"",IF(F3="",NOW(),F3),"") -> 0
A4: =TODAY() -> 46122 | B4: =NOW() -> 46122.997 | C4: 38347 | D4: =DATEDIF(Table3[[#This Row],[DOB]],TODAY(),"Y") -> 21 | E4: =EOMONTH(Table3[[#This Row],[DOB]],3) -> 38442 | F4: =IF(A4<>"",IF(F4="",NOW(),F4),"") -> 0

Sheet Scenario Summary
B2: Scenario Summary
D3: Current Values: | E3: medium | F3: high | G3: low
E4: Created by DELL on 4/10/2026 | F4: Created by DELL on 4/10/2026 | G4: Created by DELL on 4/10/2026
B5: Changing Cells:
C6: $N$23 | D6: 2799.96 | E6: 2799.96 | F6: 2799.96 | G6: 2799.96
C7: $N$22 | D7: 3499.95 | E7: 3499.95 | F7: 3499.95 | G7: 3499.95
C8: $N$24 | D8: 999.96 | E8: 999.96 | F8: 999.96 | G8: 999.96
B9: Result Cells:
C10: $AE$3
B11: Notes: Current Values column represents values of changing cells at
B12: time Scenario Summary Report was created. Changing cells for each
B13: scenario are highlighted in gray.

Sheet goal Seek
A2: Transaction_ID | B2: Date | C2: Customer_ID | D2: Customer_Name | E2: Product_ID | F2: Product_Name | G2: Category | H2: Quantity | I2: Unit_Price | J2: Payment_Method | K2: Region | L2: Customer_Segment | M2: Customer_Since | N2: Total_Amount | O2: Total goal seek
A3: TRX0139 | B3: 45399 | C3: CUST021 | D3: Kevin Scott | E3: P005 | F3: Blender | G3: Appliances | H3: 3 | I3: 333.33333 | J3: PayPal | K3: South | L3: Standard | M3: 45262 | N3: 179.97 | O3: =H3*I3 -> 1000
A4: TRX0043 | B4: 45400 | C4: CUST046 | D4: Kathleen Bennett | E4: P005 | F4: Blender | G4: Appliances | H4: 3 | I4: 500 | J4: Cash | K4: North | L4: Premium | M4: 45114 | N4: 179.97 | O4: =H4*I4 -> 1500
A5: TRX0212 | B5: 45400 | C5: CUST003 | D5: Michael Brown | E5: P008 | F5: Bookshelf | G5: Furniture | H5: 13.334222 | I5: 149.99 | J5: Credit Card | K5: North | L5: Premium | M5: 45295 | N5: 749.95 | O5: =H5*I5 -> 2000

Sheet Linear Regression
A1: SUMMARY OUTPUT | G1: Quantity | H1: Total_Amount | I1: Y = mX + c
G2: 5 | H2: 749.97 | I2: =(($K$12*G2)+$K$13) -> 430.86821 | J2: Calculation for Slope & Intercept
A3: Regression Statistics | G3: 14 | H3: 1499.94 | I3: =(($K$12*G3)+$K$13) -> 887.87413 | J3: Mean (of X) | K3: Mean (of Y) | L3: Deviations (of X) | M3: Deviations (of Y) | N3: Product of Deviations | O3: Sum of Product of Deviations | P3: Square of Deviations (of X) | Q3: Sum of Square of Deviations (of X)
A4: Multiple R | B4: 0.45808036 | G4: 10 | H4: 179.97 | I4: =(($K$12*G4)+$K$13) -> 684.76039 | J4: =AVERAGE(G2:G5) -> 10.25 | K4: =AVERAGE(H2:H5) -> 697.455 | L4: =$J$4-G2 -> 5.25 | M4: =$K$4-H2 -> -52.515 | N4: =M4*L4 -> -275.70375 | O4: =SUM(N4:N7) -> 2272.335 | P4: =L4*L4 -> 27.5625 | Q4: =SUM(P4:P7) -> 44.75
A5: R Square | B5: 0.20983762 | G5: 12 | H5: 359.94 | I5: =(($K$12*G5)+$K$13) -> 786.31726 | L5: =$J$4-G3 -> -3.75 | M5: =$K$4-H3 -> -802.485 | N5: =M5*L5 -> 3009.3187 | P5: =L5*L5 -> 14.0625
A6: Adjusted R Square | B6: 0.20665148 | G6: 4 | I6: =(($K$12*G6)+$K$13) -> 380.08978 | L6: =$J$4-G4 -> 0.25 | M6: =$K$4-H4 -> 517.485 | N6: =M6*L6 -> 129.37125 | P6: =L6*L6 -> 0.0625
A7: Standard Error | B7: 919.60715 | G7: 2 | I7: =(($K$12*G7)+$K$13) -> 278.53291 | L7: =$J$4-G5 -> -1.75 | M7: =$K$4-H5 -> 337.515 | N7: =M7*L7 -> -590.65125 | P7: =L7*L7 -> 3.0625
A8: Observations | B8: 250 | G8: 5 | I8: =(($K$12*G8)+$K$13) -> 430.86821
J9: Slope (m) = Sum of Product of Deviations / Sum of Square of deviation for X
A10: ANOVA | J10: Intercept (c) = Mean of Y - (m * Mean of X)
B11: df | C11: SS | D11: MS | E11: F | F11: Significance F
A12: Regression | B12: 1 | C12: 55695917 | D12: 55695917 | E12: 65.859537 | F12: 2.2586479e-14 | J12: Slope (m) = | K12: =O4/Q4 -> 50.778436
A13: Residual | B13: 248 | C13: 2.0972797e+08 | D13: 845677.32 | J13: Intercept (c) = | K13: =K4-(K12*J4) -> 176.97603
A14: Total | B14: 249 | C14: 2.6542389e+08
B16: Coefficients | C16: Standard Error | D16: t Stat | E16: P-value | F16: Lower 95% | G16: Upper 95% | H16: Lower 95.0% | I16: Upper 95.0%
A17: Intercept | B17: -148.85465 | C17: 143.61334 | D17: -1.0364959 | E17: 0.3009804 | F17: -431.712 | G17: 134.0027 | H17: -431.712 | I17: 134.0027
A18: Quantity | B18: 353.793 | C18: 43.595323 | D18: 8.1153889 | E18: 2.2586479e-14 | F18: 267.92872 | G18: 439.65729 | H18: 267.92872 | I18: 439.65729

Sheet GroupBy 
A1: Customer_Name | B1: Sum of Total_Amount | D1: Customer_Name | E1: Total_Amount | F1: Value
A2: Arthur Edwards | B2: 1559.94 | D2: Paul Baker | E2: 749.97 | F2: =IF(SUMIF(RawData!D:D,RawData!D2,RawData!N:N)>5000,"High Value","Normal") -> High Value
A3: Barbara Young | B3: 10649.8 | D3: Joseph Jackson | E3: 749.97 | F3: =IF(SUMIF(RawData!D:D,RawData!D3,RawData!N:N)>5000,"High Value","Normal") -> High Value
A4: Betty Campbell | B4: 5649.84 | D4: Kevin Scott | E4: 179.97 | F4: =IF(SUMIF(RawData!D:D,RawData!D4,RawData!N:N)>5000,"High Value","Normal") -> Normal
A5: Carol Evans | B5: 1149.93 | D5: Kathleen Bennett | E5: 179.97 | F5: =IF(SUMIF(RawData!D:D,RawData!D5,RawData!N:N)>5000,"High Value","Normal") -> Normal
A6: Charles Allen | B6: 5089.73 | D6: Michael Brown | E6: 749.95 | F6: =IF(SUMIF(RawData!D:D,RawData!D6,RawData!N:N)>5000,"High Value","Normal") -> High Value
A7: Cynthia Price | B7: 3769.83 | D7: Dorothy Nelson | E7: 119.98 | F7: =IF(SUMIF(RawData!D:D,RawData!D7,RawData!N:N)>5000,"High Value","Normal") -> High Value
A8: Daniel King | B8: 7309.8 | D8: Dorothy Nelson | E8: 749.95 | F8: =IF(SUMIF(RawData!D:D,RawData!D8,RawData!N:N)>5000,"High Value","Normal") -> High Value
A9: David Martinez | B9: 1809.84 | D9: Charles Allen | E9: 179.97 | F9: =IF(SUMIF(RawData!D:D,RawData!D9,RawData!N:N)>5000,"High Value","Normal") -> High Value
A10: Dennis Gray | B10: 479.92 | D10: Robert Thomas | E10: 2699.97 | F10: =IF(SUMIF(RawData!D:D,RawData!D10,RawData!N:N)>5000,"High Value","Normal") -> Normal
A11: Dorothy Nelson | B11: 8269.79 | D11: Karen Hill | E11: 179.97 | F11: =IF(SUMIF(RawData!D:D,RawData!D11,RawData!N:N)>5000,"High Value","Normal") -> High Value
A12: Douglas Watson | B12: 4829.89 | D12: Susan Green | E12: 149.99 | F12: =IF(SUMIF(RawData!D:D,RawData!D12,RawData!N:N)>5000,"High Value","Normal") -> Normal
A13: Edward Mitchell | B13: 11919.77 | D13: Kathleen Bennett | E13: 749.95 | F13: =IF(SUMIF(RawData!D:D,RawData!D13,RawData!N:N)>5000,"High Value","Normal") -> Normal
... A51: William White | B51: 4749.91 | D51: Paul Baker | E51: 4499.95 | F51: =IF(SUMIF(RawData!D:D,RawData!D51,RawData!N:N)>5000,"High Value","Normal") -> High Value
D52: Edward Mitchell | E52: 4499.95 | F52: =IF(SUMIF(RawData!D:D,RawData!D52,RawData!N:N)>5000,"High Value","Normal") -> High Value
D53: Betty Campbell | E53: 59.99 | F53: =IF(SUMIF(RawData!D:D,RawData!D53,RawData!N:N)>5000,"High Value","Normal") -> High Value
D54: Jennifer Taylor | E54: 599.98 | F54: =IF(SUMIF(RawData!D:D,RawData!D54,RawData!N:N)>5000,"High Value","Normal") -> Normal
D55: Raymond Ross | E55: 359.96 | F55: =IF(SUMIF(RawData!D:D,RawData!D55,RawData!N:N)>5000,"High Value","Normal") -> Normal
D56: Kevin Scott | E56: 79.99 | F56: =IF(SUMIF(RawData!D:D,RawData!D56,RawData!N:N)>5000,"High Value","Normal") -> Normal
D57: Robert Thomas | E57: 179.98 | F57: =IF(SUMIF(RawData!D:D,RawData!D57,RawData!N:N)>5000,"High Value","Normal") -> Normal
D58: Kathleen Bennett | E58: 2099.97 | F58: =IF(SUMIF(RawData!D:D,RawData!D58,RawData!N:N)>5000,"High Value","Normal") -> Normal
D59: Patricia Moore | E59: 3599.96 | F59: =IF(SUMIF(RawData!D:D,RawData!D59,RawData!N:N)>5000,"High Value","Normal") -> High Value
D60: Helen Roberts | E60: 149.99 | F60: =IF(SUMIF(RawData!D:D,RawData!D60,RawData!N:N)>5000,"High Value","Normal") -> High Value
D61: Emma Wilson | E61: 179.98 | F61: =IF(SUMIF(RawData!D:D,RawData!D61,RawData!N:N)>5000,"High Value","Normal") -> Normal
D62: Charles Allen | E62: 89.99 | F62: =IF(SUMIF(RawData!D:D,RawData!D62,RawData!N:N)>5000,"High Value","Normal") -> High Value
D63: Susan Green | E63: 89.99 | F63: =IF(SUMIF(RawData!D:D,RawData!D63,RawData!N:N)>5000,"High Value","Normal") -> Normal
... D251: Steven Turner | E251: 269.97 | F251: =IF(SUMIF(RawData!D:D,RawData!D251,RawData!N:N)>5000,"High Value","Normal") -> Normal

Sheet PivotTable
A1: Category | B1: Sum of Total_Amount | D1: Region | E1: Sum of Total_Amount | G1: Month | H1: Sum of Total_Amount | J1: Customer_Segment | K1: Sum of Total_Amount | M1: Row Labels | N1: Sum of Quantity
A2: Appliances | B2: 8338.74 | D2: Central | E2: 41288.34 | G2: Jan | H2: 25799.15 | J2: Basic | K2: 62177.81 | M2: Blender | N2: 87
A3: Electronics | B3: 171756.05 | D3: East | E3: 59288.39 | G3: Feb | H3: 16069.38 | J3: Premium | K3: 84657.12 | M3: Bookshelf | N3: 102
A4: Furniture | B4: 49097.68 | D4: North | E4: 50808.31 | G4: Mar | H4: 19899.38 | J4: Standard | K4: 82357.54 | M4: Coffee Maker | N4: 39
D5: South | E5: 36398.75 | G5: Apr | H5: 27899.16 | M5: Desk | N5: 78
D6: West | E6: 41408.68 | G6: May | H6: 17039.35 | M6: Headphones | N6: 47
G7: Jun | H7: 19299.45 | M7: Keyboard | N7: 89
G8: Jul | H8: 18479.4 | M8: Laptop | N8: 75
G9: Aug | H9: 15759.43 | M9: Monitor | N9: 88
G10: Sep | H10: 12989.51 | M10: Office Chair | N10: 52
G11: Oct | H11: 20609.52 | M11: Smartphone | N11: 96
G12: Nov | H12: 12309.44
G13: Dec | H13: 23039.3

Sheet Dashboard
A7: Total Revenue
A8: =SUM('[1]Raw Data'!N2:N10000) -> 229192.47
A11: Transactions
A12: =COUNTA('[1]Raw Data'!A2:A10000) -> 250
A15: Customers
A16: =SUMPRODUCT(1/COUNTIF('[1]Raw Data'!C2:C251,'[1]Raw Data'!C2:C251)) -> 50
A19: Avg Order
A20: =IFERROR(AVERAGE('[1]Raw Data'!N2:N10000),0) -> 916.76988
